{
  "imDbId": "tt2442560",
  "title": "Peaky Blinders",
  "fullTitle": "Peaky Blinders (TV Series 2013–2022)",
  "type": "TVSeries",
  "year": "2013",
  "episodes": [
    {
      "id": "tt2471500",
      "seasonNumber": "1",
      "episodeNumber": "1",
      "title": "Episode #1.1",
      "image": "https://m.media-amazon.com/images/M/MV5BMDI0NjZlOWEtOTA5MS00MGExLTk1ZDMtMzk0ZTE3YzYzZGIxXkEyXkFqcGdeQXVyNDg4MjkzNDk@._V1_Ratio1.7778_AL_.jpg",
      "year": "2014",
      "released": "30 Sep. 2014",
      "plot": "Thomas Shelby plans to fix a horse race; some guns turn up stolen.",
      "imDbRating": "8.0",
      "imDbRatingCount": "12060"
    },
    {
      "id": "tt2471502",
      "seasonNumber": "1",
      "episodeNumber": "2",
      "title": "Episode #1.2",
      "image": "https://m.media-amazon.com/images/M/MV5BMjE2ZjIxZDAtZDA5ZC00ODI5LWFkMjgtNjE4ZmZmMzliNDk5XkEyXkFqcGdeQXVyNDg4MjkzNDk@._V1_Ratio1.7778_AL_.jpg",
      "year": "2014",
      "released": "30 Sep. 2014",
      "plot": "Thomas Shelby starts a feud with a gypsy family and finally meets with Inspector Campbell to talk about the stolen guns.",
      "imDbRating": "8.2",
      "imDbRatingCount": "10150"
    },
    {
      "id": "tt2471506",
      "seasonNumber": "1",
      "episodeNumber": "3",
      "title": "Episode #1.3",
      "image": "https://m.media-amazon.com/images/M/MV5BMTQyMDg2ODE4OF5BMl5BanBnXkFtZTgwNDA1MjE0MDE@._V1_Ratio1.7778_AL_.jpg",
      "year": "2014",
      "released": "30 Sep. 2014",
      "plot": "Thomas is livid to find out that Ada and Freddie are married; IRA sympathizers tries to get information from Thomas about the stolen guns.",
      "imDbRating": "8.1",
      "imDbRatingCount": "9514"
    },
    {
      "id": "tt2461634",
      "seasonNumber": "1",
      "episodeNumber": "4",
      "title": "Episode #1.4",
      "image": "https://m.media-amazon.com/images/M/MV5BNjEwOTE3Y2EtYmViNS00N2MxLWExN2QtODVmMTM2OGNiMDgzXkEyXkFqcGdeQXVyNDg4MjkzNDk@._V1_Ratio1.7778_AL_.jpg",
      "year": "2014",
      "released": "30 Sep. 2014",
      "plot": "Thomas attempts to make a deal with Campbell; The Peaky's war with the Lees intensifies.",
      "imDbRating": "8.5",
      "imDbRatingCount": "9305"
    },
    {
      "id": "tt2461632",
      "seasonNumber": "1",
      "episodeNumber": "5",
      "title": "Episode #1.5",
      "image": "https://m.media-amazon.com/images/M/MV5BNGZiZDZjZTQtZTQzMi00NzBjLWJiZGQtNWE4MzY0MzdhY2FhXkEyXkFqcGdeQXVyNDg4MjkzNDk@._V1_Ratio1.7778_AL_.jpg",
      "year": "2014",
      "released": "30 Sep. 2014",
      "plot": "The Shelbys get a surprise visit by an almost forgotten relative. Thomas has one more dangerous plan with the cops.",
      "imDbRating": "8.8",
      "imDbRatingCount": "9764"
    },
    {
      "id": "tt2461638",
      "seasonNumber": "1",
      "episodeNumber": "6",
      "title": "Episode #1.6",
      "image": "https://m.media-amazon.com/images/M/MV5BZGVmOTA1NWYtZTcwYi00ZTNkLWFjNTctOGRlYzU1NjZjN2JkXkEyXkFqcGdeQXVyNDg4MjkzNDk@._V1_Ratio1.7778_AL_.jpg",
      "year": "2014",
      "released": "30 Sep. 2014",
      "plot": "Tommy and the Peaky Blinders prepare for a big operation, that quickly becomes way trickier than they thought.",
      "imDbRating": "9.1",
      "imDbRatingCount": "10892"
    }
  ],
  "errorMessage": ""
}