{
  "imDbId": "tt0979432",
  "title": "Boardwalk Empire",
  "fullTitle": "Boardwalk Empire (TV Series 2010–2014)",
  "type": "TVSeries",
  "year": "2010",
  "description": "64 wins & 184 nominations",
  "items": [
    {
      "eventTitle": "Primetime Emmy Awards",
      "awardEventDetails": [
        {
          "image": "https://m.media-amazon.com/images/M/MV5BMTk4MDM0NDg4NV5BMl5BanBnXkFtZTcwMzgwNTgxOA@@._V1_Ratio1.0000_AL_.jpg",
          "title": "2015 Nominee Primetime Emmy",
          "for": "Outstanding Directing for a Drama Series",
          "description": "Timothy Van Patten (For Eldorado (2014))"
        },
        {
          "image": "https://m.media-amazon.com/images/M/MV5BMjI4MzU2MTkzOV5BMl5BanBnXkFtZTgwNDYxNzIzNzE@._V1_Ratio1.4800_AL_.jpg",
          "title": "2015 Nominee Primetime Emmy",
          "for": "Outstanding Sound Editing for a Series",
          "description": "Fred Rosenberg (supervising sound editor) - Bill Orrico (sound editor) - Roland Vajs (sound editor) - Ruy García (sound effects editor) - Jeffrey Stern (dialogue editor) - Annette Kudrak (music editor) - Steven Visscher (foley editor) - Marko A. Costanzo (foley artist) (For episode: \"The Good Listener\".)"
        },
        {
          "image": "https://imdb-api.com/images/original/nopicture.jpg",
          "title": "2015 Nominee Primetime Emmy",
          "for": "Outstanding Prosthetic Makeup for a Series, Limited Series, Movie or a Special",
          "description": "Michele Paris (department head makeup artist) - Joseph Farulla (key makeup artist) (For episode \"The Good Listener\")"
        },
        {
          "image": "https://m.media-amazon.com/images/M/MV5BMTYzNzExOTQ2MF5BMl5BanBnXkFtZTcwMzA1OTYzNw@@._V1_Ratio1.0000_AL_.jpg",
          "title": "2015 Winner Primetime Emmy",
          "for": "Outstanding Production Design for a Narrative Period Program (One Hour or More)",
          "description": "Bill Groom (production designer) - Adam Scher (art director) - Carol Silverman (set decorator) (For episode: \"Golden Days For Boys And Girls\", \"Friendless Child and \"Eldorado\". Tied with The Knick (2014).)"
        },
        {
          "image": "https://m.media-amazon.com/images/M/MV5BNjlkOGI0NTEtNmVlZi00Y2VlLWE1ZGQtODRhZDIxNmRmNzgxXkEyXkFqcGdeQXVyMTE4NTQ5Mw@@._V1_Ratio1.0000_AL_.jpg",
          "title": "2015 Winner Primetime Emmy",
          "for": "Outstanding Cinematography for a Single-Camera Series",
          "description": "Jonathan Freeman (director of photography) (For episode: \"Golden Days for Boys and Girls\".)"
        }
      ]
    },
    {
      "eventTitle": "BAFTA Awards",
      "awardEventDetails": [
        {
          "image": "https://m.media-amazon.com/images/M/MV5BMTcyNDA4Nzk3N15BMl5BanBnXkFtZTcwNDYzMjMxMw@@._V1_Ratio1.0000_AL_.jpg",
          "title": "2011 Nominee BAFTA TV Award",
          "for": "Best International",
          "description": "Martin Scorsese - Terence Winter - Timothy Van Patten - Howard Korder"
        }
      ]
    },
    {
      "eventTitle": "Writers Guild of America, USA",
      "awardEventDetails": [
        {
          "image": "https://imdb-api.com/images/original/nopicture.jpg",
          "title": "2015 Nominee WGA Award (TV)",
          "for": "Episodic Drama",
          "description": "Howard Korder"
        },
        {
          "image": "https://m.media-amazon.com/images/M/MV5BMjA4Mjk3MDYwMV5BMl5BanBnXkFtZTgwMjI2MDY0NDE@._V1_Ratio1.0000_AL_.jpg",
          "title": "2015 Nominee WGA Award (TV)",
          "for": "Episodic Drama",
          "description": "Riccardo DiLoreto - Cristine Chambers - Howard Korder"
        },
        {
          "image": "https://m.media-amazon.com/images/M/MV5BMTI4MzE2NDUxMF5BMl5BanBnXkFtZTcwNDY2NjEzMQ@@._V1_Ratio1.0000_AL_.jpg",
          "title": "2013 Nominee WGA Award (TV)",
          "for": "Dramatic Series",
          "description": "David Flebotte (as Dave Flebotte) - Diane Frolov - Chris Haddock - Rolin Jones - Howard Korder - Steve Kornacki - Andrew Schneider - David Stenn - Terence Winter"
        },
        {
          "image": "https://imdb-api.com/images/original/nopicture.jpg",
          "title": "2012 Nominee WGA Award (TV)",
          "for": "Episodic Drama",
          "description": "Itamar Moses (For A Dangerous Maid (2011).)"
        },
        {
          "image": "https://imdb-api.com/images/original/nopicture.jpg",
          "title": "2012 Nominee WGA Award (TV)",
          "for": "Episodic Drama",
          "description": "Bathsheba Doran (For The Age of Reason (2011).)"
        }
      ]
    },
    {
      "eventTitle": "Image Awards (NAACP)",
      "awardEventDetails": [
        {
          "image": "https://m.media-amazon.com/images/M/MV5BMjI1NDYyNzk4OV5BMl5BanBnXkFtZTgwNDAyMzI1MDI@._V1_Ratio1.5200_AL_.jpg",
          "title": "2015 Nominee Image Award",
          "for": "Outstanding Supporting Actor in a Drama Series",
          "description": "Jeffrey Wright"
        },
        {
          "image": "https://m.media-amazon.com/images/M/MV5BYTYxNzc5ZmYtODcyNi00ZWUwLWExNWUtY2Y0YTlhZDBlMGU1XkEyXkFqcGdeQXVyNzQ1ODk3MTQ@._V1_Ratio0.7027_AL_.jpg",
          "title": "2014 Nominee Image Award",
          "for": "Outstanding Drama Series",
          "description": ""
        },
        {
          "image": "https://m.media-amazon.com/images/M/MV5BMjI1NDYyNzk4OV5BMl5BanBnXkFtZTgwNDAyMzI1MDI@._V1_Ratio1.5200_AL_.jpg",
          "title": "2014 Nominee Image Award",
          "for": "Outstanding Supporting Actor in a Drama Series",
          "description": "Jeffrey Wright"
        },
        {
          "image": "https://m.media-amazon.com/images/M/MV5BMjE1MTI1NjUxMV5BMl5BanBnXkFtZTgwNTUyODM0MTE@._V1_Ratio1.0000_AL_.jpg",
          "title": "2014 Nominee Image Award",
          "for": "Outstanding Supporting Actor in a Drama Series",
          "description": "Michael Kenneth Williams"
        },
        {
          "image": "https://m.media-amazon.com/images/M/MV5BYTYxNzc5ZmYtODcyNi00ZWUwLWExNWUtY2Y0YTlhZDBlMGU1XkEyXkFqcGdeQXVyNzQ1ODk3MTQ@._V1_Ratio0.7027_AL_.jpg",
          "title": "2013 Nominee Image Award",
          "for": "Outstanding Drama Series",
          "description": ""
        }
      ]
    },
    {
      "eventTitle": "Screen Actors Guild Awards",
      "awardEventDetails": [
        {
          "image": "https://m.media-amazon.com/images/M/MV5BODc0NTU3NDA4M15BMl5BanBnXkFtZTcwNDkxNzQxNA@@._V1_Ratio1.0000_AL_.jpg",
          "title": "2015 Nominee Actor",
          "for": "Outstanding Performance by a Male Actor in a Drama Series",
          "description": "Steve Buscemi"
        },
        {
          "image": "https://m.media-amazon.com/images/M/MV5BODc0NTU3NDA4M15BMl5BanBnXkFtZTcwNDkxNzQxNA@@._V1_Ratio1.0000_AL_.jpg",
          "title": "2015 Nominee Actor",
          "for": "Outstanding Performance by an Ensemble in a Drama Series",
          "description": "Steve Buscemi - Paul Calderon - Nicholas E. Calhoun - Louis Cancelmi - John Ellison Conlee - Michael Countryman - Stephen Graham - Domenick Lombardozzi - Nolan Lyons - Kelly Macdonald - Boris McGiver - Vincent Piazza - Paul Sparks - Travis Tope - Shea Whigham - Anatol Yusef - Michael Zegen"
        },
        {
          "image": "https://m.media-amazon.com/images/M/MV5BNzYwMDIyMTA1Ml5BMl5BanBnXkFtZTcwMDQ1ODgzMQ@@._V1_Ratio1.0000_AL_.jpg",
          "title": "2015 Nominee Actor",
          "for": "Outstanding Action Performance by a Stunt Ensemble in a Television Series",
          "description": "Christopher Place"
        },
        {
          "image": "https://m.media-amazon.com/images/M/MV5BODc0NTU3NDA4M15BMl5BanBnXkFtZTcwNDkxNzQxNA@@._V1_Ratio1.0000_AL_.jpg",
          "title": "2014 Nominee Actor",
          "for": "Outstanding Performance by a Male Actor in a Drama Series",
          "description": "Steve Buscemi"
        },
        {
          "image": "https://m.media-amazon.com/images/M/MV5BMTQ5Njg0NjkxMV5BMl5BanBnXkFtZTcwMzc0NTI5NA@@._V1_Ratio1.0000_AL_.jpg",
          "title": "2014 Nominee Actor",
          "for": "Outstanding Performance by an Ensemble in a Drama Series",
          "description": "Patricia Arquette - Margot Bingham - Steve Buscemi - Brian Geraghty - Stephen Graham - Erik LaRay Harvey - Jack Huston - Ron Livingston - Domenick Lombardozzi - Gretchen Mol - Ben Rosenfield - Michael Stuhlbarg - Jacob A. Ware - Shea Whigham - Michael Kenneth Williams - Jeffrey Wright - Paul Sparks"
        }
      ]
    },
    {
      "eventTitle": "Costume Designers Guild Awards",
      "awardEventDetails": [
        {
          "image": "https://m.media-amazon.com/images/M/MV5BMTU2NjQwMjAxM15BMl5BanBnXkFtZTgwMDA0MjA1NDE@._V1_Ratio1.0000_AL_.jpg",
          "title": "2015 Nominee CDG Award",
          "for": "Outstanding Period/Fantasy Television Series",
          "description": "John Dunn"
        },
        {
          "image": "https://m.media-amazon.com/images/M/MV5BMTU2NjQwMjAxM15BMl5BanBnXkFtZTgwMDA0MjA1NDE@._V1_Ratio1.0000_AL_.jpg",
          "title": "2014 Nominee CDG Award",
          "for": "Outstanding Period/Fantasy Television Series",
          "description": "John Dunn - Lisa Padovani"
        },
        {
          "image": "https://m.media-amazon.com/images/M/MV5BMTU2NjQwMjAxM15BMl5BanBnXkFtZTgwMDA0MjA1NDE@._V1_Ratio1.0000_AL_.jpg",
          "title": "2013 Nominee CDG Award",
          "for": "Outstanding Period/Fantasy Television Series",
          "description": "John Dunn - Lisa Padovani"
        },
        {
          "image": "https://m.media-amazon.com/images/M/MV5BMTU2NjQwMjAxM15BMl5BanBnXkFtZTgwMDA0MjA1NDE@._V1_Ratio1.0000_AL_.jpg",
          "title": "2012 Winner CDG Award",
          "for": "Outstanding Period/Fantasy Television Series",
          "description": "John Dunn - Lisa Padovani"
        },
        {
          "image": "https://m.media-amazon.com/images/M/MV5BMTU2NjQwMjAxM15BMl5BanBnXkFtZTgwMDA0MjA1NDE@._V1_Ratio1.0000_AL_.jpg",
          "title": "2011 Winner CDG Award",
          "for": "Outstanding Period/Fantasy Television Series",
          "description": "John Dunn - Lisa Padovani"
        }
      ]
    },
    {
      "eventTitle": "American Society of Cinematographers, USA",
      "awardEventDetails": [
        {
          "image": "https://m.media-amazon.com/images/M/MV5BNjlkOGI0NTEtNmVlZi00Y2VlLWE1ZGQtODRhZDIxNmRmNzgxXkEyXkFqcGdeQXVyMTE4NTQ5Mw@@._V1_Ratio1.0000_AL_.jpg",
          "title": "2015 Winner ASC Award",
          "for": "Outstanding Achievement in Cinematography in Regular Series",
          "description": "Jonathan Freeman (Episode: \"Golden Days for Boys and Girls (2014)\")"
        },
        {
          "image": "https://imdb-api.com/images/original/nopicture.jpg",
          "title": "2014 Nominee ASC Award",
          "for": "Outstanding Achievement in Cinematography in One-Hour Episodic Television Series",
          "description": "David Franco (Episode: \"Erlkönig (2013)\")"
        },
        {
          "image": "https://imdb-api.com/images/original/nopicture.jpg",
          "title": "2012 Nominee ASC Award",
          "for": "Outstanding Achievement in Cinematography in One-Hour Episodic/Pilot Television",
          "description": "David Franco (Episode: \"To the Lost (2011)\")"
        },
        {
          "image": "https://m.media-amazon.com/images/M/MV5BNjlkOGI0NTEtNmVlZi00Y2VlLWE1ZGQtODRhZDIxNmRmNzgxXkEyXkFqcGdeQXVyMTE4NTQ5Mw@@._V1_Ratio1.0000_AL_.jpg",
          "title": "2012 Winner ASC Award",
          "for": "Outstanding Achievement in Cinematography in One-Hour Episodic/Pilot Television",
          "description": "Jonathan Freeman (Episode: \"21 (2011)\")"
        },
        {
          "image": "https://m.media-amazon.com/images/M/MV5BNjlkOGI0NTEtNmVlZi00Y2VlLWE1ZGQtODRhZDIxNmRmNzgxXkEyXkFqcGdeQXVyMTE4NTQ5Mw@@._V1_Ratio1.0000_AL_.jpg",
          "title": "2011 Winner ASC Award",
          "for": "Outstanding Achievement in Cinematography in Regular Series One Episode/Pilot",
          "description": "Jonathan Freeman (Episode: \"Home (2010)\")"
        }
      ]
    },
    {
      "eventTitle": "Hollywood Makeup Artist and Hair Stylist Guild Awards",
      "awardEventDetails": [
        {
          "image": "https://imdb-api.com/images/original/nopicture.jpg",
          "title": "2015 Nominee Artisan",
          "for": "Best Period and/or Character Makeup - Television and New Media Series",
          "description": "Michele Paris - Joseph Farulla"
        },
        {
          "image": "https://imdb-api.com/images/original/nopicture.jpg",
          "title": "2015 Nominee Artisan",
          "for": "Best Special Makeup Effects - Television and New Media Series",
          "description": "Michele Paris - Joseph Farulla"
        },
        {
          "image": "https://imdb-api.com/images/original/nopicture.jpg",
          "title": "2014 Winner Artisan",
          "for": "Best Period and/or Character Makeup - Television and New Media Series",
          "description": "Michele Paris"
        }
      ]
    },
    {
      "eventTitle": "Cinema Audio Society, USA",
      "awardEventDetails": [
        {
          "image": "https://m.media-amazon.com/images/M/MV5BZjE4ZDdiZWMtZWEwNi00N2FlLWFjZWQtN2QxYzE3M2Y5YmI5XkEyXkFqcGdeQXVyMTMxMTIwMTE0._V1_Ratio1.0000_AL_.jpg",
          "title": "2015 Nominee C.A.S. Award",
          "for": "Outstanding Achievement in Sound Mixing for Television Series - One Hour",
          "description": "Frank Stettner (production mixer) - Tom Fleischman (re-recording mixer) - Mark DeSimone (ADR mixer) - George A. Lara (foley mixer) (Episode: \"Friendless Child (2014)\")"
        },
        {
          "image": "https://m.media-amazon.com/images/M/MV5BZjE4ZDdiZWMtZWEwNi00N2FlLWFjZWQtN2QxYzE3M2Y5YmI5XkEyXkFqcGdeQXVyMTMxMTIwMTE0._V1_Ratio1.0000_AL_.jpg",
          "title": "2014 Nominee C.A.S. Award",
          "for": "Outstanding Achievement in Sound Mixing for Television Series - One Hour",
          "description": "Frank Stettner (production mixer) - Tom Fleischman (re-recording mixer) - Mark DeSimone (adr mixer) - George A. Lara (foley mixer) (Episode: \"Erlkönig (2013)\")"
        },
        {
          "image": "https://m.media-amazon.com/images/M/MV5BZjE4ZDdiZWMtZWEwNi00N2FlLWFjZWQtN2QxYzE3M2Y5YmI5XkEyXkFqcGdeQXVyMTMxMTIwMTE0._V1_Ratio1.0000_AL_.jpg",
          "title": "2013 Nominee C.A.S. Award",
          "for": "Outstanding Achievement in Sound Mixing for Television Series - One Hour",
          "description": "Frank Stettner (production mixer) - Tom Fleischman (re-recording mixer) (Episode: \"The Milkmaid's Lot (2012)\")"
        },
        {
          "image": "https://m.media-amazon.com/images/M/MV5BZjE4ZDdiZWMtZWEwNi00N2FlLWFjZWQtN2QxYzE3M2Y5YmI5XkEyXkFqcGdeQXVyMTMxMTIwMTE0._V1_Ratio1.0000_AL_.jpg",
          "title": "2012 Winner C.A.S. Award",
          "for": "Outstanding Achievement in Sound Mixing for Television Series",
          "description": "Frank Stettner (production mixer) - Tom Fleischman (re-recording mixer) (Episode: \"To the Lost (2011)\")"
        },
        {
          "image": "https://m.media-amazon.com/images/M/MV5BZjE4ZDdiZWMtZWEwNi00N2FlLWFjZWQtN2QxYzE3M2Y5YmI5XkEyXkFqcGdeQXVyMTMxMTIwMTE0._V1_Ratio1.0000_AL_.jpg",
          "title": "2011 Winner C.A.S. Award",
          "for": "Outstanding Achievement in Sound Mixing for Television Series",
          "description": "Frank Stettner (production mixer) - Tom Fleischman (re-recording mixer) (Episode: \"A Return to Normalcy (2010)\")"
        }
      ]
    },
    {
      "eventTitle": "Online Film & Television Association",
      "awardEventDetails": [
        {
          "image": "https://m.media-amazon.com/images/M/MV5BYTYxNzc5ZmYtODcyNi00ZWUwLWExNWUtY2Y0YTlhZDBlMGU1XkEyXkFqcGdeQXVyNzQ1ODk3MTQ@._V1_Ratio0.7027_AL_.jpg",
          "title": "2015 Nominee OFTA Television Award",
          "for": "Best Production Design in a Series",
          "description": ""
        },
        {
          "image": "https://m.media-amazon.com/images/M/MV5BYTYxNzc5ZmYtODcyNi00ZWUwLWExNWUtY2Y0YTlhZDBlMGU1XkEyXkFqcGdeQXVyNzQ1ODk3MTQ@._V1_Ratio0.7027_AL_.jpg",
          "title": "2015 Nominee OFTA Television Award",
          "for": "Best Costume Design in a Series",
          "description": ""
        },
        {
          "image": "https://m.media-amazon.com/images/M/MV5BYTYxNzc5ZmYtODcyNi00ZWUwLWExNWUtY2Y0YTlhZDBlMGU1XkEyXkFqcGdeQXVyNzQ1ODk3MTQ@._V1_Ratio0.7027_AL_.jpg",
          "title": "2015 Nominee OFTA Television Award",
          "for": "Best Makeup/Hairstyling in a Series",
          "description": ""
        },
        {
          "image": "https://m.media-amazon.com/images/M/MV5BYTYxNzc5ZmYtODcyNi00ZWUwLWExNWUtY2Y0YTlhZDBlMGU1XkEyXkFqcGdeQXVyNzQ1ODk3MTQ@._V1_Ratio0.7027_AL_.jpg",
          "title": "2015 Nominee OFTA Television Award",
          "for": "Best Sound in a Series",
          "description": ""
        },
        {
          "image": "https://m.media-amazon.com/images/M/MV5BMTk4MDM0NDg4NV5BMl5BanBnXkFtZTcwMzgwNTgxOA@@._V1_Ratio1.0000_AL_.jpg",
          "title": "2014 Nominee OFTA Television Award",
          "for": "Best Direction in a Drama Series",
          "description": "Timothy Van Patten - Allen Coulter - Jeremy Podeswa - Ed Bianchi - Alik Sakharov - Jake Paltrow"
        }
      ]
    },
    {
      "eventTitle": "Academy of Television Arts and Sciences College Television Awards",
      "awardEventDetails": [
        {
          "image": "https://imdb-api.com/images/original/nopicture.jpg",
          "title": "2015 Nominee Emmy",
          "for": "Outstanding Special Visual Effects in a Supporting Role",
          "description": "Parker Chehak"
        }
      ]
    },
    {
      "eventTitle": "Art Directors Guild",
      "awardEventDetails": [
        {
          "image": "https://m.media-amazon.com/images/M/MV5BMTYzNzExOTQ2MF5BMl5BanBnXkFtZTcwMzA1OTYzNw@@._V1_Ratio1.0000_AL_.jpg",
          "title": "2015 Nominee Excellence in Production Design Award",
          "for": "One Hour Period or Fantasy Single-Camera Television Series",
          "description": "Bill Groom (production designer) - Adam Scher (art director) - Dan Kuchar (assistant art director) - Emily Beck (assistant art director) - Larry M. Gruber (assistant art director) - Ariel Poster (graphic artist) - Ted Haigh (graphic designer) - Jan Jericho (illustrator) - Jon Ringbom (scenic artist) - Carol Silverman (set decorator) (Episode: \"Golden Days for Boys and Girls (2014)\")"
        },
        {
          "image": "https://m.media-amazon.com/images/M/MV5BMTYzNzExOTQ2MF5BMl5BanBnXkFtZTcwMzA1OTYzNw@@._V1_Ratio1.0000_AL_.jpg",
          "title": "2014 Nominee Excellence in Production Design Award",
          "for": "One Hour Single-Camera Television Series",
          "description": "Bill Groom (production designer) - Adam Scher (art director) - Dan Kuchar (assistant art director) - Emily Beck (assistant art director) - Larry M. Gruber (assistant art director) - Neil Prince (assistant art director) - Ariel Poster (graphic artist) - Ted Haigh (graphic designer) - Jan Jericho (illustrator) - Jon Ringbom (scenic artist) - Carol Silverman (set decorator) (Episode: \"Old Ship of Zion\")"
        },
        {
          "image": "https://m.media-amazon.com/images/M/MV5BMTYzNzExOTQ2MF5BMl5BanBnXkFtZTcwMzA1OTYzNw@@._V1_Ratio1.0000_AL_.jpg",
          "title": "2013 Nominee Excellence in Production Design Award",
          "for": "Episode of a One Hour Single-Camera Television Series",
          "description": "Bill Groom (production designer) - Adam Scher (art director) - Larry M. Gruber (assistant art director) - Emily Beck (assistant art director) - Dan Kuchar (assistant art director) - Barbra Matis (assistant art director) - Miguel López-Castillo (assistant art director) - Jan Jericho (illustrator) - Ted Haigh (graphic designer) - Jon Ringbom (scenic artist) - Carol Silverman (set decorator) (Episode: \"Resolution\")"
        },
        {
          "image": "https://m.media-amazon.com/images/M/MV5BMTYzNzExOTQ2MF5BMl5BanBnXkFtZTcwMzA1OTYzNw@@._V1_Ratio1.0000_AL_.jpg",
          "title": "2012 Winner Excellence in Production Design Award",
          "for": "Episode of a One Hour Single-Camera Television Series",
          "description": "Bill Groom (production designer) - Charley Beal (art director) - Adam Scher (art director) - Larry M. Gruber (assistant art director) - Emily Beck (assistant art director) - Ted Haigh (graphic designer) - Jon Ringbom (scenic artist) - Carol Silverman (set decorator) (For episode \"21\")"
        }
      ]
    },
    {
      "eventTitle": "Hollywood Post Alliance, US",
      "awardEventDetails": [
        {
          "image": "https://imdb-api.com/images/original/nopicture.jpg",
          "title": "2015 Winner HPA Award",
          "for": "Outstanding Color Grading - Television",
          "description": "John Crowley (Episode: \"Golden Days for Boys and Girls (2014)\")"
        },
        {
          "image": "https://imdb-api.com/images/original/nopicture.jpg",
          "title": "2012 Nominee HPA Award",
          "for": "Outstanding Color Grading - Television",
          "description": "Martin Zeichner (Episode: \"21 (2011)\")"
        },
        {
          "image": "https://imdb-api.com/images/original/nopicture.jpg",
          "title": "2012 Nominee HPA Award",
          "for": "Outstanding Editing - Television",
          "description": "Kate Sanford (Episode: \"Under God's Power She Flourishes (2011)\")"
        },
        {
          "image": "https://imdb-api.com/images/original/nopicture.jpg",
          "title": "2011 Winner HPA Award",
          "for": "Outstanding Compositing - Television",
          "description": "Paul Graff - Brian Sales - Merysa Nichols - Jesse Siglow (Episode: \"Family Limitation (2010)\")"
        },
        {
          "image": "https://imdb-api.com/images/original/nopicture.jpg",
          "title": "2011 Nominee HPA Award",
          "for": "Outstanding Compositing - Television",
          "description": "J. John Corbett - Jun Zhang - Matthew Conner (Episode: \"Boardwalk Empire (2010)\")"
        }
      ]
    },
    {
      "eventTitle": "NAMIC Vision Awards",
      "awardEventDetails": [
        {
          "image": "https://m.media-amazon.com/images/M/MV5BMjE1MTI1NjUxMV5BMl5BanBnXkFtZTgwNTUyODM0MTE@._V1_Ratio1.0000_AL_.jpg",
          "title": "2015 Winner Vision Award",
          "for": "Best Performance - Drama",
          "description": "Michael Kenneth Williams"
        },
        {
          "image": "https://m.media-amazon.com/images/M/MV5BMjI1NDYyNzk4OV5BMl5BanBnXkFtZTgwNDAyMzI1MDI@._V1_Ratio1.5200_AL_.jpg",
          "title": "2015 Nominee Vision Award",
          "for": "Best Performance - Drama",
          "description": "Jeffrey Wright"
        },
        {
          "image": "https://m.media-amazon.com/images/M/MV5BMjMyNTMyOTMyNV5BMl5BanBnXkFtZTgwMzU0Nzg3MTE@._V1_Ratio1.0000_AL_.jpg",
          "title": "2015 Nominee Vision Award",
          "for": "Best Performance - Drama",
          "description": "Margot Bingham"
        },
        {
          "image": "https://m.media-amazon.com/images/M/MV5BMjE1MTI1NjUxMV5BMl5BanBnXkFtZTgwNTUyODM0MTE@._V1_Ratio1.0000_AL_.jpg",
          "title": "2014 Nominee Vision Award",
          "for": "Best Performance - Drama",
          "description": "Michael Kenneth Williams"
        },
        {
          "image": "https://m.media-amazon.com/images/M/MV5BMjI1NDYyNzk4OV5BMl5BanBnXkFtZTgwNDAyMzI1MDI@._V1_Ratio1.5200_AL_.jpg",
          "title": "2014 Winner Vision Award",
          "for": "Best Performance - Drama",
          "description": "Jeffrey Wright"
        }
      ]
    },
    {
      "eventTitle": "Location Managers Guild International Awards (LMGI)",
      "awardEventDetails": [
        {
          "image": "https://imdb-api.com/images/original/nopicture.jpg",
          "title": "2015 Winner LMGI Award",
          "for": "Outstanding Locations in a Period Television Series",
          "description": "Amanda Foley - Audra Gorman"
        }
      ]
    },
    {
      "eventTitle": "Motion Picture Sound Editors, USA",
      "awardEventDetails": [
        {
          "image": "https://imdb-api.com/images/original/nopicture.jpg",
          "title": "2014 Nominee Golden Reel Award",
          "for": "Best Sound Editing - Short Form Dialogue and ADR in Television",
          "description": "Fred Rosenberg (supervising sound editor, supervising adr editor, adr editor) - Jeffrey Stern (supervising dialogue editor, dialogue editor) - Bill Orrico (dialogue editor) - Roland Vajs (dialogue editor) (Episode: \"Havre de Grace\")"
        },
        {
          "image": "https://m.media-amazon.com/images/M/MV5BMjI4MzU2MTkzOV5BMl5BanBnXkFtZTgwNDYxNzIzNzE@._V1_Ratio1.4800_AL_.jpg",
          "title": "2014 Nominee Golden Reel Award",
          "for": "Best Sound Editing - Short Form Sound Effects and Foley in Television",
          "description": "Fred Rosenberg (supervising sound editor) - Ruy García (sound designer) - Steven Visscher (supervising foley editor) - Marko A. Costanzo (foley artist) - Bill Orrico (foley editor) - Roland Vajs (effects editor) (Episode: \"White Horse Pike\")"
        },
        {
          "image": "https://imdb-api.com/images/original/nopicture.jpg",
          "title": "2011 Winner Golden Reel Award",
          "for": "Best Sound Editing - Short Form Music in Television",
          "description": "Annette Kudrak (music editor) (Episode: \"Anastasia\")"
        }
      ]
    },
    {
      "eventTitle": "Critics Choice Television Awards",
      "awardEventDetails": [
        {
          "image": "https://m.media-amazon.com/images/M/MV5BMjI1NDYyNzk4OV5BMl5BanBnXkFtZTgwNDAyMzI1MDI@._V1_Ratio1.5200_AL_.jpg",
          "title": "2014 Nominee Critics' Choice TV Award",
          "for": "Best Supporting Actor in a Drama Series",
          "description": "Jeffrey Wright"
        },
        {
          "image": "https://m.media-amazon.com/images/M/MV5BNDc5NTU2MzY0Nl5BMl5BanBnXkFtZTcwMzU4MjA0Ng@@._V1_Ratio1.0000_AL_.jpg",
          "title": "2012 Nominee Critics' Choice TV Award",
          "for": "Best Supporting Actress in a Drama Series",
          "description": "Kelly Macdonald"
        },
        {
          "image": "https://m.media-amazon.com/images/M/MV5BYTYxNzc5ZmYtODcyNi00ZWUwLWExNWUtY2Y0YTlhZDBlMGU1XkEyXkFqcGdeQXVyNzQ1ODk3MTQ@._V1_Ratio0.7027_AL_.jpg",
          "title": "2011 Nominee Critics' Choice TV Award",
          "for": "Best Drama Series",
          "description": ""
        },
        {
          "image": "https://m.media-amazon.com/images/M/MV5BODc0NTU3NDA4M15BMl5BanBnXkFtZTcwNDkxNzQxNA@@._V1_Ratio1.0000_AL_.jpg",
          "title": "2011 Nominee Critics' Choice TV Award",
          "for": "Best Actor in a Drama Series",
          "description": "Steve Buscemi"
        },
        {
          "image": "https://m.media-amazon.com/images/M/MV5BMTczMDM3MTE1M15BMl5BanBnXkFtZTcwOTI4Njg2Ng@@._V1_Ratio1.0000_AL_.jpg",
          "title": "2011 Nominee Critics' Choice TV Award",
          "for": "Best Supporting Actor in a Drama Series",
          "description": "Michael Pitt"
        }
      ]
    },
    {
      "eventTitle": "Guild of Music Supervisors Awards",
      "awardEventDetails": [
        {
          "image": "https://m.media-amazon.com/images/M/MV5BZjc1MmQwMzctODk5Ni00MzkwLWIxNWUtOGY0ODIyMDdhNzFiXkEyXkFqcGdeQXVyNzQ3NTE5MzI@._V1_Ratio1.5200_AL_.jpg",
          "title": "2014 Nominee GMS Award",
          "for": "Best Music Supervision for Television Drama",
          "description": "Randall Poster"
        },
        {
          "image": "https://m.media-amazon.com/images/M/MV5BZjc1MmQwMzctODk5Ni00MzkwLWIxNWUtOGY0ODIyMDdhNzFiXkEyXkFqcGdeQXVyNzQ3NTE5MzI@._V1_Ratio1.5200_AL_.jpg",
          "title": "2013 Nominee GMS Award",
          "for": "Best Music Supervision for Television Drama",
          "description": "Randall Poster"
        },
        {
          "image": "https://m.media-amazon.com/images/M/MV5BZjc1MmQwMzctODk5Ni00MzkwLWIxNWUtOGY0ODIyMDdhNzFiXkEyXkFqcGdeQXVyNzQ3NTE5MzI@._V1_Ratio1.5200_AL_.jpg",
          "title": "2011 Nominee GMS Award",
          "for": "Best Music Supervision for Television",
          "description": "Jim Dunbar - Randall Poster"
        }
      ]
    },
    {
      "eventTitle": "Golden Globes, USA",
      "awardEventDetails": [
        {
          "image": "https://m.media-amazon.com/images/M/MV5BYTYxNzc5ZmYtODcyNi00ZWUwLWExNWUtY2Y0YTlhZDBlMGU1XkEyXkFqcGdeQXVyNzQ1ODk3MTQ@._V1_Ratio0.7027_AL_.jpg",
          "title": "2013 Nominee Golden Globe",
          "for": "Best Television Series - Drama",
          "description": ""
        },
        {
          "image": "https://m.media-amazon.com/images/M/MV5BODc0NTU3NDA4M15BMl5BanBnXkFtZTcwNDkxNzQxNA@@._V1_Ratio1.0000_AL_.jpg",
          "title": "2013 Nominee Golden Globe",
          "for": "Best Performance by an Actor in a Television Series - Drama",
          "description": "Steve Buscemi"
        },
        {
          "image": "https://m.media-amazon.com/images/M/MV5BYTYxNzc5ZmYtODcyNi00ZWUwLWExNWUtY2Y0YTlhZDBlMGU1XkEyXkFqcGdeQXVyNzQ1ODk3MTQ@._V1_Ratio0.7027_AL_.jpg",
          "title": "2012 Nominee Golden Globe",
          "for": "Best Television Series - Drama",
          "description": ""
        },
        {
          "image": "https://m.media-amazon.com/images/M/MV5BODc0NTU3NDA4M15BMl5BanBnXkFtZTcwNDkxNzQxNA@@._V1_Ratio1.0000_AL_.jpg",
          "title": "2012 Nominee Golden Globe",
          "for": "Best Performance by an Actor in a Television Series - Drama",
          "description": "Steve Buscemi"
        },
        {
          "image": "https://m.media-amazon.com/images/M/MV5BNDc5NTU2MzY0Nl5BMl5BanBnXkFtZTcwMzU4MjA0Ng@@._V1_Ratio1.0000_AL_.jpg",
          "title": "2012 Nominee Golden Globe",
          "for": "Best Performance by an Actress in a Supporting Role in a Series, Miniseries or Motion Picture Made for Television",
          "description": "Kelly Macdonald"
        }
      ]
    },
    {
      "eventTitle": "Key Art Awards",
      "awardEventDetails": [
        {
          "image": "https://m.media-amazon.com/images/M/MV5BYTYxNzc5ZmYtODcyNi00ZWUwLWExNWUtY2Y0YTlhZDBlMGU1XkEyXkFqcGdeQXVyNzQ1ODk3MTQ@._V1_Ratio0.7027_AL_.jpg",
          "title": "2013 Nominee Key Art Award",
          "for": "Best Engagement",
          "description": " (For the TV spot, \"Boardwalk Empire/Uber Promotional Stunt\".)"
        }
      ]
    },
    {
      "eventTitle": "Crime Thriller Awards, UK",
      "awardEventDetails": [
        {
          "image": "https://m.media-amazon.com/images/M/MV5BYTYxNzc5ZmYtODcyNi00ZWUwLWExNWUtY2Y0YTlhZDBlMGU1XkEyXkFqcGdeQXVyNzQ1ODk3MTQ@._V1_Ratio0.7027_AL_.jpg",
          "title": "2013 Nominee Dagger",
          "for": "Best International TV Drama",
          "description": " (\"Season 3\")"
        },
        {
          "image": "https://m.media-amazon.com/images/M/MV5BNDc5NTU2MzY0Nl5BMl5BanBnXkFtZTcwMzU4MjA0Ng@@._V1_Ratio1.0000_AL_.jpg",
          "title": "2012 Winner Dagger",
          "for": "Best Supporting Actress",
          "description": "Kelly Macdonald"
        },
        {
          "image": "https://m.media-amazon.com/images/M/MV5BODc0NTU3NDA4M15BMl5BanBnXkFtZTcwNDkxNzQxNA@@._V1_Ratio1.0000_AL_.jpg",
          "title": "2012 Nominee Dagger",
          "for": "Best Leading Actor",
          "description": "Steve Buscemi"
        },
        {
          "image": "https://m.media-amazon.com/images/M/MV5BYTYxNzc5ZmYtODcyNi00ZWUwLWExNWUtY2Y0YTlhZDBlMGU1XkEyXkFqcGdeQXVyNzQ1ODk3MTQ@._V1_Ratio0.7027_AL_.jpg",
          "title": "2012 Nominee Dagger",
          "for": "Best International TV Drama",
          "description": " (\"Season 2\")"
        },
        {
          "image": "https://m.media-amazon.com/images/M/MV5BODc0NTU3NDA4M15BMl5BanBnXkFtZTcwNDkxNzQxNA@@._V1_Ratio1.0000_AL_.jpg",
          "title": "2011 Nominee Dagger",
          "for": "Best Leading Actor",
          "description": "Steve Buscemi"
        }
      ]
    },
    {
      "eventTitle": "IGN Summer Movie Awards",
      "awardEventDetails": [
        {
          "image": "https://m.media-amazon.com/images/M/MV5BMjI1NDYyNzk4OV5BMl5BanBnXkFtZTgwNDAyMzI1MDI@._V1_Ratio1.5200_AL_.jpg",
          "title": "2013 Nominee IGN Award",
          "for": "Best TV Villain",
          "description": "Jeffrey Wright (For playing \"Dr. Valentin Narcisse\".)"
        },
        {
          "image": "https://m.media-amazon.com/images/M/MV5BMTU0NzM3MzQ4Ml5BMl5BanBnXkFtZTgwOTg2MjY4ODE@._V1_Ratio1.8000_AL_.jpg",
          "title": "2012 Winner IGN Award",
          "for": "Best TV Villain",
          "description": "Bobby Cannavale (For playing \"Gyp Rosetti\".)"
        },
        {
          "image": "https://m.media-amazon.com/images/M/MV5BYTYxNzc5ZmYtODcyNi00ZWUwLWExNWUtY2Y0YTlhZDBlMGU1XkEyXkFqcGdeQXVyNzQ1ODk3MTQ@._V1_Ratio0.7027_AL_.jpg",
          "title": "2011 Nominee IGN Award",
          "for": "Best TV Episode",
          "description": " (For the episode \"Under God's Power She Flourishes\".)"
        },
        {
          "image": "https://m.media-amazon.com/images/M/MV5BYTYxNzc5ZmYtODcyNi00ZWUwLWExNWUtY2Y0YTlhZDBlMGU1XkEyXkFqcGdeQXVyNzQ1ODk3MTQ@._V1_Ratio0.7027_AL_.jpg",
          "title": "2010 Nominee IGN Award",
          "for": "Best New TV Series",
          "description": ""
        }
      ]
    },
    {
      "eventTitle": "Visual Effects Society Awards",
      "awardEventDetails": [
        {
          "image": "https://m.media-amazon.com/images/M/MV5BNzIwODBiZTgtNWFhYS00YjZkLTk5OTEtNjFhMmI1M2RjOWM4XkEyXkFqcGdeQXVyMTk0MDk1Mg@@._V1_Ratio1.0000_AL_.jpg",
          "title": "2013 Winner VES Award",
          "for": "Outstanding Supporting Visual Effects in a Broadcast Program",
          "description": "John Bair - Parker Chehak - Paul Graff - Lesley Robson-Foster (Episode: \"The Pony (2012)\")"
        },
        {
          "image": "https://m.media-amazon.com/images/M/MV5BMWY4MmU1MDgtNzBlOS00MjhlLWE2NDctODhmOTRmNzZlOGQxXkEyXkFqcGdeQXVyMjA1MjI4MjI@._V1_Ratio1.0000_AL_.jpg",
          "title": "2012 Winner VES Award",
          "for": "Outstanding Models in a Broadcast Program or Commercial",
          "description": "Matthew Conner - Eran Dinur - David W. Reynolds - Szymon Weglarski (Georgia Peaches)"
        },
        {
          "image": "https://m.media-amazon.com/images/M/MV5BMTI3NDEzNTE1MV5BMl5BanBnXkFtZTcwMTI2MzMyMw@@._V1_Ratio1.0000_AL_.jpg",
          "title": "2012 Nominee VES Award",
          "for": "Outstanding Created Environment in a Broadcast Program or Commercial",
          "description": "Matthew Conner - Robert Stromberg (\"Two Boats and a Lifeguard\")"
        },
        {
          "image": "https://m.media-amazon.com/images/M/MV5BNTZmMjE2YTktYjM0OS00YzJjLTg4M2MtZTg4NWMzN2E5NWU5XkEyXkFqcGdeQXVyMjQwMDg0Ng@@._V1_Ratio1.0000_AL_.jpg",
          "title": "2012 Nominee VES Award",
          "for": "Outstanding Supporting Visual Effects in a Broadcast Program",
          "description": "Richard Friedlander - Robert Stromberg - David Taritero (Episode: \"Georgia Peaches (2011)\")"
        },
        {
          "image": "https://m.media-amazon.com/images/M/MV5BMWY4MmU1MDgtNzBlOS00MjhlLWE2NDctODhmOTRmNzZlOGQxXkEyXkFqcGdeQXVyMjA1MjI4MjI@._V1_Ratio1.0000_AL_.jpg",
          "title": "2012 Winner VES Award",
          "for": "Outstanding Compositing in a Broadcast Program or Commercial",
          "description": "Anton Dawson - Eran Dinur - Austin Meyers - David W. Reynolds (Episode: \"Gimcrack and Bunkum (2011)\")"
        }
      ]
    },
    {
      "eventTitle": "Young Artist Awards",
      "awardEventDetails": [
        {
          "image": "https://imdb-api.com/images/original/nopicture.jpg",
          "title": "2013 Winner Young Artist Award",
          "for": "Best Performance in a TV Series - Recurring Young Actor Ten and Under",
          "description": "Rory McTigue - Declan McTigue"
        },
        {
          "image": "https://m.media-amazon.com/images/M/MV5BYzVhZWZkZTItNTZjMy00NWM5LThlNGYtMWQwZDc5ZmE4MjRmXkEyXkFqcGdeQXVyMjI5MDMzODU@._V1_Ratio1.5200_AL_.jpg",
          "title": "2013 Nominee Young Artist Award",
          "for": "Best Performance in a TV Series - Recurring Young Actress",
          "description": "Lucy Gallina - Josie Gallina"
        },
        {
          "image": "https://m.media-amazon.com/images/M/MV5BMTEwZDc1ZWYtODk0OC00NzU2LWJjNGItNmY3NWI2MDNlMTgzXkEyXkFqcGdeQXVyMjM4MTQ3OTg@._V1_Ratio1.0000_AL_.jpg",
          "title": "2012 Nominee Young Artist Award",
          "for": "Best Performance in a TV Series - Recurring Young Actor",
          "description": "Brady Noon (as Brady & Connor Noon) - Connor Noon (as Brady & Connor Noon)"
        },
        {
          "image": "https://m.media-amazon.com/images/M/MV5BYzVhZWZkZTItNTZjMy00NWM5LThlNGYtMWQwZDc5ZmE4MjRmXkEyXkFqcGdeQXVyMjI5MDMzODU@._V1_Ratio1.5200_AL_.jpg",
          "title": "2012 Nominee Young Artist Award",
          "for": "Best Performance in a TV Series - Recurring Young Actress Ten and Under",
          "description": "Lucy Gallina (as Lucy and Josie Gallina) - Josie Gallina (as Lucy and Josie Gallina)"
        }
      ]
    },
    {
      "eventTitle": "Grammy Awards",
      "awardEventDetails": [
        {
          "image": "https://m.media-amazon.com/images/M/MV5BZjc1MmQwMzctODk5Ni00MzkwLWIxNWUtOGY0ODIyMDdhNzFiXkEyXkFqcGdeQXVyNzQ3NTE5MzI@._V1_Ratio1.5200_AL_.jpg",
          "title": "2012 Winner Grammy",
          "for": "Best Compilation Soundtrack Album for Motion Picture, Television or Other Visual Media",
          "description": "Stewart Lerman (Producer) - Randall Poster (Producer) - Kevin Weaver (Producer)"
        }
      ]
    },
    {
      "eventTitle": "AFI Awards, USA",
      "awardEventDetails": [
        {
          "image": "https://m.media-amazon.com/images/M/MV5BYTYxNzc5ZmYtODcyNi00ZWUwLWExNWUtY2Y0YTlhZDBlMGU1XkEyXkFqcGdeQXVyNzQ1ODk3MTQ@._V1_Ratio0.7027_AL_.jpg",
          "title": "2012 Winner AFI Award",
          "for": "TV Program of the Year",
          "description": " (BOARDWALK EMPIRE struts into its second year with an intoxicating air, adding new layers of complexity to this sumptuous, sprawling saga of Atlantic City during Prohibition. Martin Scorsese and Terence Winter command a talented ensemble that tells a tale of America, this year uncorking the emotional inner life of Steve Buscemi's \"Nucky Thompson\" and the world he rules with an iron fist.)"
        },
        {
          "image": "https://m.media-amazon.com/images/M/MV5BYTYxNzc5ZmYtODcyNi00ZWUwLWExNWUtY2Y0YTlhZDBlMGU1XkEyXkFqcGdeQXVyNzQ1ODk3MTQ@._V1_Ratio0.7027_AL_.jpg",
          "title": "2011 Winner AFI Award",
          "for": "TV Program of the Year",
          "description": " (BOARDWALK EMPIRE struts into its second year with an intoxicating air, adding new layers of complexity to this sumptuous, sprawling saga of Atlantic City during Prohibition. Martin Scorsese and Terence Winter command a talented ensemble that tells a tale of America, this year uncorking the emotional inner life of Steve Buscemi's \"Nucky Thompson\" and the world he rules with an iron fist.)"
        }
      ]
    },
    {
      "eventTitle": "American Cinema Editors, USA",
      "awardEventDetails": [
        {
          "image": "https://imdb-api.com/images/original/nopicture.jpg",
          "title": "2012 Nominee Eddie",
          "for": "Best Edited One-Hour Series for Non-Commercial Television",
          "description": "Tim Streeto (Episode: \"To the Lost (2011)\")"
        },
        {
          "image": "https://m.media-amazon.com/images/M/MV5BZGQ5NWUzZjctMzA3Ny00YmQ0LTlmNDQtMWMzYmQ3ZjdhZDc3XkEyXkFqcGdeQXVyNTI5NjIyMw@@._V1_Ratio1.0000_AL_.jpg",
          "title": "2011 Nominee Eddie",
          "for": "Best Edited One-Hour Series for Non-Commercial Television",
          "description": "Sidney Wolinsky (Episode: \"Boardwalk Empire (2010)\")"
        }
      ]
    },
    {
      "eventTitle": "Monte-Carlo TV Festival",
      "awardEventDetails": [
        {
          "image": "https://m.media-amazon.com/images/M/MV5BODc0NTU3NDA4M15BMl5BanBnXkFtZTcwNDkxNzQxNA@@._V1_Ratio1.0000_AL_.jpg",
          "title": "2012 Nominee Golden Nymph",
          "for": "Outstanding Actor in a Drama Series",
          "description": "Steve Buscemi"
        },
        {
          "image": "https://m.media-amazon.com/images/M/MV5BMTczMDM3MTE1M15BMl5BanBnXkFtZTcwOTI4Njg2Ng@@._V1_Ratio1.0000_AL_.jpg",
          "title": "2012 Nominee Golden Nymph",
          "for": "Outstanding Actor in a Drama Series",
          "description": "Michael Pitt"
        },
        {
          "image": "https://m.media-amazon.com/images/M/MV5BNDc5NTU2MzY0Nl5BMl5BanBnXkFtZTcwMzU4MjA0Ng@@._V1_Ratio1.0000_AL_.jpg",
          "title": "2012 Nominee Golden Nymph",
          "for": "Outstanding Actress in a Drama Series",
          "description": "Kelly Macdonald"
        },
        {
          "image": "https://m.media-amazon.com/images/M/MV5BMTI0ODU1Njg1MV5BMl5BanBnXkFtZTcwODcwODQzMQ@@._V1_Ratio1.0000_AL_.jpg",
          "title": "2012 Nominee Golden Nymph",
          "for": "Outstanding Actress in a Drama Series",
          "description": "Gretchen Mol"
        },
        {
          "image": "https://m.media-amazon.com/images/M/MV5BMTcyNDA4Nzk3N15BMl5BanBnXkFtZTcwNDYzMjMxMw@@._V1_Ratio1.0000_AL_.jpg",
          "title": "2012 Nominee Golden Nymph",
          "for": "Outstanding International Producer (Drama Series)",
          "description": "Martin Scorsese - Mark Wahlberg - Terence Winter - Timothy Van Patten - Stephen Levinson"
        }
      ]
    },
    {
      "eventTitle": "Banff Television Festival",
      "awardEventDetails": [
        {
          "image": "https://m.media-amazon.com/images/M/MV5BMTg1MTQxMzQxN15BMl5BanBnXkFtZTYwODY3NDg0._V1_Ratio1.0000_AL_.jpg",
          "title": "2012 Winner Banff Rockie Award",
          "for": "Best Continuing Series",
          "description": "Terence Winter (writer) - Timothy Van Patten (director) (For episode '21' (USA))"
        },
        {
          "image": "https://m.media-amazon.com/images/M/MV5BMTk4MDM0NDg4NV5BMl5BanBnXkFtZTcwMzgwNTgxOA@@._V1_Ratio1.0000_AL_.jpg",
          "title": "2011 Nominee Banff Rockie Award",
          "for": "Best Continuing Series",
          "description": "Timothy Van Patten - Martin Scorsese - Terence Winter - Howard Korder (For episode 'Boardwalk Empire' (USA))"
        }
      ]
    },
    {
      "eventTitle": "PGA Awards",
      "awardEventDetails": [
        {
          "image": "https://m.media-amazon.com/images/M/MV5BMTcyNDA4Nzk3N15BMl5BanBnXkFtZTcwNDYzMjMxMw@@._V1_Ratio1.0000_AL_.jpg",
          "title": "2012 Winner PGA Award",
          "for": "Outstanding Producer of Episodic Television, Drama",
          "description": "Eugene Kelly - Howard Korder - Stephen Levinson - Martin Scorsese - Rudd Simmons - Timothy Van Patten - Terence Winter"
        }
      ]
    },
    {
      "eventTitle": "Women's Image Network Awards",
      "awardEventDetails": [
        {
          "image": "https://m.media-amazon.com/images/M/MV5BNDc5NTU2MzY0Nl5BMl5BanBnXkFtZTcwMzU4MjA0Ng@@._V1_Ratio1.0000_AL_.jpg",
          "title": "2012 Nominee WIN Award",
          "for": "Actress Drama Series",
          "description": "Kelly Macdonald"
        }
      ]
    },
    {
      "eventTitle": "Directors Guild of America, USA",
      "awardEventDetails": [
        {
          "image": "https://m.media-amazon.com/images/M/MV5BNDk3MTIyODU0NF5BMl5BanBnXkFtZTgwMzkwNTg4NjE@._V1_Ratio1.3600_AL_.jpg",
          "title": "2011 Nominee DGA Award",
          "for": "Outstanding Directorial Achievement in Dramatic Series",
          "description": "Allen Coulter (For episode \"Paris Green\")"
        },
        {
          "image": "https://m.media-amazon.com/images/M/MV5BMTcyNDA4Nzk3N15BMl5BanBnXkFtZTcwNDYzMjMxMw@@._V1_Ratio1.0000_AL_.jpg",
          "title": "2011 Winner DGA Award",
          "for": "Outstanding Directorial Achievement in Dramatic Series",
          "description": "Martin Scorsese - Harvey Waldman (unit production manager) (plaque) - Christopher Surgent (first assistant director) (plaque) - Takahide Kawakami (second assistant director) (plaque) - April Taylor (second assistant director/location manager) (plaque) - Regina Heyman (second assistant director/location manager) (plaque) - Patrick McDonald (second second assistant director) (plaque) - Salvatore E. Sutera (additional second assistant director) (plaque) (For episode \"Boardwalk Empire\")"
        }
      ]
    },
    {
      "eventTitle": "Television Critics Association Awards",
      "awardEventDetails": [
        {
          "image": "https://m.media-amazon.com/images/M/MV5BYTYxNzc5ZmYtODcyNi00ZWUwLWExNWUtY2Y0YTlhZDBlMGU1XkEyXkFqcGdeQXVyNzQ1ODk3MTQ@._V1_Ratio0.7027_AL_.jpg",
          "title": "2011 Nominee TCA Award",
          "for": "Program of the Year",
          "description": ""
        },
        {
          "image": "https://m.media-amazon.com/images/M/MV5BYTYxNzc5ZmYtODcyNi00ZWUwLWExNWUtY2Y0YTlhZDBlMGU1XkEyXkFqcGdeQXVyNzQ1ODk3MTQ@._V1_Ratio0.7027_AL_.jpg",
          "title": "2011 Nominee TCA Award",
          "for": "Outstanding New Program",
          "description": ""
        },
        {
          "image": "https://m.media-amazon.com/images/M/MV5BODc0NTU3NDA4M15BMl5BanBnXkFtZTcwNDkxNzQxNA@@._V1_Ratio1.0000_AL_.jpg",
          "title": "2011 Nominee TCA Award",
          "for": "Individual Achievement in Drama",
          "description": "Steve Buscemi"
        }
      ]
    },
    {
      "eventTitle": "Casting Society of America, USA",
      "awardEventDetails": [
        {
          "image": "https://m.media-amazon.com/images/M/MV5BOWFlMGQ3ZTktZWM1Mi00MzY5LTkxNDUtNDgxNWIxZjZiNDcxXkEyXkFqcGdeQXVyMjQwMDg0Ng@@._V1_Ratio1.0000_AL_.jpg",
          "title": "2011 Winner Artios Award",
          "for": "Outstanding Achievement in Casting - Television Pilot - Drama",
          "description": "Ellen Lewis (Casting Director)"
        }
      ]
    },
    {
      "eventTitle": "Satellite Awards",
      "awardEventDetails": [
        {
          "image": "https://m.media-amazon.com/images/M/MV5BNDc5NTU2MzY0Nl5BMl5BanBnXkFtZTcwMzU4MjA0Ng@@._V1_Ratio1.0000_AL_.jpg",
          "title": "2011 Nominee Satellite Award",
          "for": "Best Actress in a Supporting Role in a Series, Mini-Series or Motion Picture Made for Television",
          "description": "Kelly Macdonald"
        },
        {
          "image": "https://m.media-amazon.com/images/M/MV5BYTYxNzc5ZmYtODcyNi00ZWUwLWExNWUtY2Y0YTlhZDBlMGU1XkEyXkFqcGdeQXVyNzQ1ODk3MTQ@._V1_Ratio0.7027_AL_.jpg",
          "title": "2011 Nominee Satellite Award",
          "for": "Best Television Series, Drama",
          "description": ""
        },
        {
          "image": "https://m.media-amazon.com/images/M/MV5BODc0NTU3NDA4M15BMl5BanBnXkFtZTcwNDkxNzQxNA@@._V1_Ratio1.0000_AL_.jpg",
          "title": "2011 Nominee Satellite Award",
          "for": "Best Actor in a Series, Drama",
          "description": "Steve Buscemi"
        },
        {
          "image": "https://m.media-amazon.com/images/M/MV5BYTYxNzc5ZmYtODcyNi00ZWUwLWExNWUtY2Y0YTlhZDBlMGU1XkEyXkFqcGdeQXVyNzQ1ODk3MTQ@._V1_Ratio0.7027_AL_.jpg",
          "title": "2010 Nominee Satellite Award",
          "for": "Best Television Series, Drama",
          "description": ""
        }
      ]
    },
    {
      "eventTitle": "GALECA: The Society of LGBTQ Entertainment Critics",
      "awardEventDetails": [
        {
          "image": "https://m.media-amazon.com/images/M/MV5BYTYxNzc5ZmYtODcyNi00ZWUwLWExNWUtY2Y0YTlhZDBlMGU1XkEyXkFqcGdeQXVyNzQ1ODk3MTQ@._V1_Ratio0.7027_AL_.jpg",
          "title": "2011 Nominee Dorian Award",
          "for": "TV Drama of the Year",
          "description": ""
        }
      ]
    },
    {
      "eventTitle": "Gold Derby Awards",
      "awardEventDetails": [
        {
          "image": "https://m.media-amazon.com/images/M/MV5BYTYxNzc5ZmYtODcyNi00ZWUwLWExNWUtY2Y0YTlhZDBlMGU1XkEyXkFqcGdeQXVyNzQ1ODk3MTQ@._V1_Ratio0.7027_AL_.jpg",
          "title": "2011 Nominee Gold Derby TV Award",
          "for": "Drama Series",
          "description": ""
        },
        {
          "image": "https://m.media-amazon.com/images/M/MV5BODc0NTU3NDA4M15BMl5BanBnXkFtZTcwNDkxNzQxNA@@._V1_Ratio1.0000_AL_.jpg",
          "title": "2011 Nominee Gold Derby TV Award",
          "for": "Drama Lead Actor",
          "description": "Steve Buscemi"
        },
        {
          "image": "https://m.media-amazon.com/images/M/MV5BNDc5NTU2MzY0Nl5BMl5BanBnXkFtZTcwMzU4MjA0Ng@@._V1_Ratio1.0000_AL_.jpg",
          "title": "2011 Nominee Gold Derby TV Award",
          "for": "Drama Supporting Actress",
          "description": "Kelly Macdonald"
        }
      ]
    },
    {
      "eventTitle": "Il Festival Nazionale del Doppiaggio Voci nell'Ombra",
      "awardEventDetails": [
        {
          "image": "https://imdb-api.com/images/original/nopicture.jpg",
          "title": "2011 Nominee TV Award",
          "for": "Best Dubbing Direction",
          "description": "Sonia Scotti"
        }
      ]
    }
  ],
  "awardsHtml": "<div class=\"awards\">\r\n    <h5>64 wins & 184 nominations</h5>\r\n    <h3>Primetime Emmy Awards</h3>\r\n    <table>\r\n        <tbody>\r\n            <tr>\r\n                <td>\r\n                    <b>2015 Nominee Primetime Emmy</b>\r\n                    <br />\r\n                    Outstanding Directing for a Drama Series\r\n                    <br />\r\n                    Timothy Van Patten (For Eldorado (2014))\r\n                </td>\r\n            </tr>\r\n            <tr>\r\n                <td>\r\n                    <b>2015 Nominee Primetime Emmy</b>\r\n                    <br />\r\n                    Outstanding Sound Editing for a Series\r\n                    <br />\r\n                    Fred Rosenberg (supervising sound editor) - Bill Orrico (sound editor) - Roland Vajs (sound editor) - Ruy García (sound effects editor) - Jeffrey Stern (dialogue editor) - Annette Kudrak (music editor) - Steven Visscher (foley editor) - Marko A. Costanzo (foley artist) (For episode: \"The Good Listener\".)\r\n                </td>\r\n            </tr>\r\n            <tr>\r\n                <td>\r\n                    <b>2015 Nominee Primetime Emmy</b>\r\n                    <br />\r\n                    Outstanding Prosthetic Makeup for a Series, Limited Series, Movie or a Special\r\n                    <br />\r\n                    Michele Paris (department head makeup artist) - Joseph Farulla (key makeup artist) (For episode \"The Good Listener\")\r\n                </td>\r\n            </tr>\r\n            <tr>\r\n                <td>\r\n                    <b>2015 Winner Primetime Emmy</b>\r\n                    <br />\r\n                    Outstanding Production Design for a Narrative Period Program (One Hour or More)\r\n                    <br />\r\n                    Bill Groom (production designer) - Adam Scher (art director) - Carol Silverman (set decorator) (For episode: \"Golden Days For Boys And Girls\", \"Friendless Child and \"Eldorado\". Tied with The Knick (2014).)\r\n                </td>\r\n            </tr>\r\n            <tr>\r\n                <td>\r\n                    <b>2015 Winner Primetime Emmy</b>\r\n                    <br />\r\n                    Outstanding Cinematography for a Single-Camera Series\r\n                    <br />\r\n                    Jonathan Freeman (director of photography) (For episode: \"Golden Days for Boys and Girls\".)\r\n                </td>\r\n            </tr>\r\n        </tbody>\r\n    </table>\r\n    <h3>BAFTA Awards</h3>\r\n    <table>\r\n        <tbody>\r\n            <tr>\r\n                <td>\r\n                    <b>2011 Nominee BAFTA TV Award</b>\r\n                    <br />\r\n                    Best International\r\n                    <br />\r\n                    Martin Scorsese - Terence Winter - Timothy Van Patten - Howard Korder\r\n                </td>\r\n            </tr>\r\n        </tbody>\r\n    </table>\r\n    <h3>Writers Guild of America, USA</h3>\r\n    <table>\r\n        <tbody>\r\n            <tr>\r\n                <td>\r\n                    <b>2015 Nominee WGA Award (TV)</b>\r\n                    <br />\r\n                    Episodic Drama\r\n                    <br />\r\n                    Howard Korder\r\n                </td>\r\n            </tr>\r\n            <tr>\r\n                <td>\r\n                    <b>2015 Nominee WGA Award (TV)</b>\r\n                    <br />\r\n                    Episodic Drama\r\n                    <br />\r\n                    Riccardo DiLoreto - Cristine Chambers - Howard Korder\r\n                </td>\r\n            </tr>\r\n            <tr>\r\n                <td>\r\n                    <b>2013 Nominee WGA Award (TV)</b>\r\n                    <br />\r\n                    Dramatic Series\r\n                    <br />\r\n                    David Flebotte (as Dave Flebotte) - Diane Frolov - Chris Haddock - Rolin Jones - Howard Korder - Steve Kornacki - Andrew Schneider - David Stenn - Terence Winter\r\n                </td>\r\n            </tr>\r\n            <tr>\r\n                <td>\r\n                    <b>2012 Nominee WGA Award (TV)</b>\r\n                    <br />\r\n                    Episodic Drama\r\n                    <br />\r\n                    Itamar Moses (For A Dangerous Maid (2011).)\r\n                </td>\r\n            </tr>\r\n            <tr>\r\n                <td>\r\n                    <b>2012 Nominee WGA Award (TV)</b>\r\n                    <br />\r\n                    Episodic Drama\r\n                    <br />\r\n                    Bathsheba Doran (For The Age of Reason (2011).)\r\n                </td>\r\n            </tr>\r\n        </tbody>\r\n    </table>\r\n    <h3>Image Awards (NAACP)</h3>\r\n    <table>\r\n        <tbody>\r\n            <tr>\r\n                <td>\r\n                    <b>2015 Nominee Image Award</b>\r\n                    <br />\r\n                    Outstanding Supporting Actor in a Drama Series\r\n                    <br />\r\n                    Jeffrey Wright\r\n                </td>\r\n            </tr>\r\n            <tr>\r\n                <td>\r\n                    <b>2014 Nominee Image Award</b>\r\n                    <br />\r\n                    Outstanding Drama Series\r\n                </td>\r\n            </tr>\r\n            <tr>\r\n                <td>\r\n                    <b>2014 Nominee Image Award</b>\r\n                    <br />\r\n                    Outstanding Supporting Actor in a Drama Series\r\n                    <br />\r\n                    Jeffrey Wright\r\n                </td>\r\n            </tr>\r\n            <tr>\r\n                <td>\r\n                    <b>2014 Nominee Image Award</b>\r\n                    <br />\r\n                    Outstanding Supporting Actor in a Drama Series\r\n                    <br />\r\n                    Michael Kenneth Williams\r\n                </td>\r\n            </tr>\r\n            <tr>\r\n                <td>\r\n                    <b>2013 Nominee Image Award</b>\r\n                    <br />\r\n                    Outstanding Drama Series\r\n                </td>\r\n            </tr>\r\n        </tbody>\r\n    </table>\r\n    <h3>Screen Actors Guild Awards</h3>\r\n    <table>\r\n        <tbody>\r\n            <tr>\r\n                <td>\r\n                    <b>2015 Nominee Actor</b>\r\n                    <br />\r\n                    Outstanding Performance by a Male Actor in a Drama Series\r\n                    <br />\r\n                    Steve Buscemi\r\n                </td>\r\n            </tr>\r\n            <tr>\r\n                <td>\r\n                    <b>2015 Nominee Actor</b>\r\n                    <br />\r\n                    Outstanding Performance by an Ensemble in a Drama Series\r\n                    <br />\r\n                    Steve Buscemi - Paul Calderon - Nicholas E. Calhoun - Louis Cancelmi - John Ellison Conlee - Michael Countryman - Stephen Graham - Domenick Lombardozzi - Nolan Lyons - Kelly Macdonald - Boris McGiver - Vincent Piazza - Paul Sparks - Travis Tope - Shea Whigham - Anatol Yusef - Michael Zegen\r\n                </td>\r\n            </tr>\r\n            <tr>\r\n                <td>\r\n                    <b>2015 Nominee Actor</b>\r\n                    <br />\r\n                    Outstanding Action Performance by a Stunt Ensemble in a Television Series\r\n                    <br />\r\n                    Christopher Place\r\n                </td>\r\n            </tr>\r\n            <tr>\r\n                <td>\r\n                    <b>2014 Nominee Actor</b>\r\n                    <br />\r\n                    Outstanding Performance by a Male Actor in a Drama Series\r\n                    <br />\r\n                    Steve Buscemi\r\n                </td>\r\n            </tr>\r\n            <tr>\r\n                <td>\r\n                    <b>2014 Nominee Actor</b>\r\n                    <br />\r\n                    Outstanding Performance by an Ensemble in a Drama Series\r\n                    <br />\r\n                    Patricia Arquette - Margot Bingham - Steve Buscemi - Brian Geraghty - Stephen Graham - Erik LaRay Harvey - Jack Huston - Ron Livingston - Domenick Lombardozzi - Gretchen Mol - Ben Rosenfield - Michael Stuhlbarg - Jacob A. Ware - Shea Whigham - Michael Kenneth Williams - Jeffrey Wright - Paul Sparks\r\n                </td>\r\n            </tr>\r\n        </tbody>\r\n    </table>\r\n    <h3>Costume Designers Guild Awards</h3>\r\n    <table>\r\n        <tbody>\r\n            <tr>\r\n                <td>\r\n                    <b>2015 Nominee CDG Award</b>\r\n                    <br />\r\n                    Outstanding Period/Fantasy Television Series\r\n                    <br />\r\n                    John Dunn\r\n                </td>\r\n            </tr>\r\n            <tr>\r\n                <td>\r\n                    <b>2014 Nominee CDG Award</b>\r\n                    <br />\r\n                    Outstanding Period/Fantasy Television Series\r\n                    <br />\r\n                    John Dunn - Lisa Padovani\r\n                </td>\r\n            </tr>\r\n            <tr>\r\n                <td>\r\n                    <b>2013 Nominee CDG Award</b>\r\n                    <br />\r\n                    Outstanding Period/Fantasy Television Series\r\n                    <br />\r\n                    John Dunn - Lisa Padovani\r\n                </td>\r\n            </tr>\r\n            <tr>\r\n                <td>\r\n                    <b>2012 Winner CDG Award</b>\r\n                    <br />\r\n                    Outstanding Period/Fantasy Television Series\r\n                    <br />\r\n                    John Dunn - Lisa Padovani\r\n                </td>\r\n            </tr>\r\n            <tr>\r\n                <td>\r\n                    <b>2011 Winner CDG Award</b>\r\n                    <br />\r\n                    Outstanding Period/Fantasy Television Series\r\n                    <br />\r\n                    John Dunn - Lisa Padovani\r\n                </td>\r\n            </tr>\r\n        </tbody>\r\n    </table>\r\n    <h3>American Society of Cinematographers, USA</h3>\r\n    <table>\r\n        <tbody>\r\n            <tr>\r\n                <td>\r\n                    <b>2015 Winner ASC Award</b>\r\n                    <br />\r\n                    Outstanding Achievement in Cinematography in Regular Series\r\n                    <br />\r\n                    Jonathan Freeman (Episode: \"Golden Days for Boys and Girls (2014)\")\r\n                </td>\r\n            </tr>\r\n            <tr>\r\n                <td>\r\n                    <b>2014 Nominee ASC Award</b>\r\n                    <br />\r\n                    Outstanding Achievement in Cinematography in One-Hour Episodic Television Series\r\n                    <br />\r\n                    David Franco (Episode: \"Erlkönig (2013)\")\r\n                </td>\r\n            </tr>\r\n            <tr>\r\n                <td>\r\n                    <b>2012 Nominee ASC Award</b>\r\n                    <br />\r\n                    Outstanding Achievement in Cinematography in One-Hour Episodic/Pilot Television\r\n                    <br />\r\n                    David Franco (Episode: \"To the Lost (2011)\")\r\n                </td>\r\n            </tr>\r\n            <tr>\r\n                <td>\r\n                    <b>2012 Winner ASC Award</b>\r\n                    <br />\r\n                    Outstanding Achievement in Cinematography in One-Hour Episodic/Pilot Television\r\n                    <br />\r\n                    Jonathan Freeman (Episode: \"21 (2011)\")\r\n                </td>\r\n            </tr>\r\n            <tr>\r\n                <td>\r\n                    <b>2011 Winner ASC Award</b>\r\n                    <br />\r\n                    Outstanding Achievement in Cinematography in Regular Series One Episode/Pilot\r\n                    <br />\r\n                    Jonathan Freeman (Episode: \"Home (2010)\")\r\n                </td>\r\n            </tr>\r\n        </tbody>\r\n    </table>\r\n    <h3>Hollywood Makeup Artist and Hair Stylist Guild Awards</h3>\r\n    <table>\r\n        <tbody>\r\n            <tr>\r\n                <td>\r\n                    <b>2015 Nominee Artisan</b>\r\n                    <br />\r\n                    Best Period and/or Character Makeup - Television and New Media Series\r\n                    <br />\r\n                    Michele Paris - Joseph Farulla\r\n                </td>\r\n            </tr>\r\n            <tr>\r\n                <td>\r\n                    <b>2015 Nominee Artisan</b>\r\n                    <br />\r\n                    Best Special Makeup Effects - Television and New Media Series\r\n                    <br />\r\n                    Michele Paris - Joseph Farulla\r\n                </td>\r\n            </tr>\r\n            <tr>\r\n                <td>\r\n                    <b>2014 Winner Artisan</b>\r\n                    <br />\r\n                    Best Period and/or Character Makeup - Television and New Media Series\r\n                    <br />\r\n                    Michele Paris\r\n                </td>\r\n            </tr>\r\n        </tbody>\r\n    </table>\r\n    <h3>Cinema Audio Society, USA</h3>\r\n    <table>\r\n        <tbody>\r\n            <tr>\r\n                <td>\r\n                    <b>2015 Nominee C.A.S. Award</b>\r\n                    <br />\r\n                    Outstanding Achievement in Sound Mixing for Television Series - One Hour\r\n                    <br />\r\n                    Frank Stettner (production mixer) - Tom Fleischman (re-recording mixer) - Mark DeSimone (ADR mixer) - George A. Lara (foley mixer) (Episode: \"Friendless Child (2014)\")\r\n                </td>\r\n            </tr>\r\n            <tr>\r\n                <td>\r\n                    <b>2014 Nominee C.A.S. Award</b>\r\n                    <br />\r\n                    Outstanding Achievement in Sound Mixing for Television Series - One Hour\r\n                    <br />\r\n                    Frank Stettner (production mixer) - Tom Fleischman (re-recording mixer) - Mark DeSimone (adr mixer) - George A. Lara (foley mixer) (Episode: \"Erlkönig (2013)\")\r\n                </td>\r\n            </tr>\r\n            <tr>\r\n                <td>\r\n                    <b>2013 Nominee C.A.S. Award</b>\r\n                    <br />\r\n                    Outstanding Achievement in Sound Mixing for Television Series - One Hour\r\n                    <br />\r\n                    Frank Stettner (production mixer) - Tom Fleischman (re-recording mixer) (Episode: \"The Milkmaid's Lot (2012)\")\r\n                </td>\r\n            </tr>\r\n            <tr>\r\n                <td>\r\n                    <b>2012 Winner C.A.S. Award</b>\r\n                    <br />\r\n                    Outstanding Achievement in Sound Mixing for Television Series\r\n                    <br />\r\n                    Frank Stettner (production mixer) - Tom Fleischman (re-recording mixer) (Episode: \"To the Lost (2011)\")\r\n                </td>\r\n            </tr>\r\n            <tr>\r\n                <td>\r\n                    <b>2011 Winner C.A.S. Award</b>\r\n                    <br />\r\n                    Outstanding Achievement in Sound Mixing for Television Series\r\n                    <br />\r\n                    Frank Stettner (production mixer) - Tom Fleischman (re-recording mixer) (Episode: \"A Return to Normalcy (2010)\")\r\n                </td>\r\n            </tr>\r\n        </tbody>\r\n    </table>\r\n    <h3>Online Film & Television Association</h3>\r\n    <table>\r\n        <tbody>\r\n            <tr>\r\n                <td>\r\n                    <b>2015 Nominee OFTA Television Award</b>\r\n                    <br />\r\n                    Best Production Design in a Series\r\n                </td>\r\n            </tr>\r\n            <tr>\r\n                <td>\r\n                    <b>2015 Nominee OFTA Television Award</b>\r\n                    <br />\r\n                    Best Costume Design in a Series\r\n                </td>\r\n            </tr>\r\n            <tr>\r\n                <td>\r\n                    <b>2015 Nominee OFTA Television Award</b>\r\n                    <br />\r\n                    Best Makeup/Hairstyling in a Series\r\n                </td>\r\n            </tr>\r\n            <tr>\r\n                <td>\r\n                    <b>2015 Nominee OFTA Television Award</b>\r\n                    <br />\r\n                    Best Sound in a Series\r\n                </td>\r\n            </tr>\r\n            <tr>\r\n                <td>\r\n                    <b>2014 Nominee OFTA Television Award</b>\r\n                    <br />\r\n                    Best Direction in a Drama Series\r\n                    <br />\r\n                    Timothy Van Patten - Allen Coulter - Jeremy Podeswa - Ed Bianchi - Alik Sakharov - Jake Paltrow\r\n                </td>\r\n            </tr>\r\n        </tbody>\r\n    </table>\r\n    <h3>Academy of Television Arts and Sciences College Television Awards</h3>\r\n    <table>\r\n        <tbody>\r\n            <tr>\r\n                <td>\r\n                    <b>2015 Nominee Emmy</b>\r\n                    <br />\r\n                    Outstanding Special Visual Effects in a Supporting Role\r\n                    <br />\r\n                    Parker Chehak\r\n                </td>\r\n            </tr>\r\n        </tbody>\r\n    </table>\r\n    <h3>Art Directors Guild</h3>\r\n    <table>\r\n        <tbody>\r\n            <tr>\r\n                <td>\r\n                    <b>2015 Nominee Excellence in Production Design Award</b>\r\n                    <br />\r\n                    One Hour Period or Fantasy Single-Camera Television Series\r\n                    <br />\r\n                    Bill Groom (production designer) - Adam Scher (art director) - Dan Kuchar (assistant art director) - Emily Beck (assistant art director) - Larry M. Gruber (assistant art director) - Ariel Poster (graphic artist) - Ted Haigh (graphic designer) - Jan Jericho (illustrator) - Jon Ringbom (scenic artist) - Carol Silverman (set decorator) (Episode: \"Golden Days for Boys and Girls (2014)\")\r\n                </td>\r\n            </tr>\r\n            <tr>\r\n                <td>\r\n                    <b>2014 Nominee Excellence in Production Design Award</b>\r\n                    <br />\r\n                    One Hour Single-Camera Television Series\r\n                    <br />\r\n                    Bill Groom (production designer) - Adam Scher (art director) - Dan Kuchar (assistant art director) - Emily Beck (assistant art director) - Larry M. Gruber (assistant art director) - Neil Prince (assistant art director) - Ariel Poster (graphic artist) - Ted Haigh (graphic designer) - Jan Jericho (illustrator) - Jon Ringbom (scenic artist) - Carol Silverman (set decorator) (Episode: \"Old Ship of Zion\")\r\n                </td>\r\n            </tr>\r\n            <tr>\r\n                <td>\r\n                    <b>2013 Nominee Excellence in Production Design Award</b>\r\n                    <br />\r\n                    Episode of a One Hour Single-Camera Television Series\r\n                    <br />\r\n                    Bill Groom (production designer) - Adam Scher (art director) - Larry M. Gruber (assistant art director) - Emily Beck (assistant art director) - Dan Kuchar (assistant art director) - Barbra Matis (assistant art director) - Miguel López-Castillo (assistant art director) - Jan Jericho (illustrator) - Ted Haigh (graphic designer) - Jon Ringbom (scenic artist) - Carol Silverman (set decorator) (Episode: \"Resolution\")\r\n                </td>\r\n            </tr>\r\n            <tr>\r\n                <td>\r\n                    <b>2012 Winner Excellence in Production Design Award</b>\r\n                    <br />\r\n                    Episode of a One Hour Single-Camera Television Series\r\n                    <br />\r\n                    Bill Groom (production designer) - Charley Beal (art director) - Adam Scher (art director) - Larry M. Gruber (assistant art director) - Emily Beck (assistant art director) - Ted Haigh (graphic designer) - Jon Ringbom (scenic artist) - Carol Silverman (set decorator) (For episode \"21\")\r\n                </td>\r\n            </tr>\r\n        </tbody>\r\n    </table>\r\n    <h3>Hollywood Post Alliance, US</h3>\r\n    <table>\r\n        <tbody>\r\n            <tr>\r\n                <td>\r\n                    <b>2015 Winner HPA Award</b>\r\n                    <br />\r\n                    Outstanding Color Grading - Television\r\n                    <br />\r\n                    John Crowley (Episode: \"Golden Days for Boys and Girls (2014)\")\r\n                </td>\r\n            </tr>\r\n            <tr>\r\n                <td>\r\n                    <b>2012 Nominee HPA Award</b>\r\n                    <br />\r\n                    Outstanding Color Grading - Television\r\n                    <br />\r\n                    Martin Zeichner (Episode: \"21 (2011)\")\r\n                </td>\r\n            </tr>\r\n            <tr>\r\n                <td>\r\n                    <b>2012 Nominee HPA Award</b>\r\n                    <br />\r\n                    Outstanding Editing - Television\r\n                    <br />\r\n                    Kate Sanford (Episode: \"Under God's Power She Flourishes (2011)\")\r\n                </td>\r\n            </tr>\r\n            <tr>\r\n                <td>\r\n                    <b>2011 Winner HPA Award</b>\r\n                    <br />\r\n                    Outstanding Compositing - Television\r\n                    <br />\r\n                    Paul Graff - Brian Sales - Merysa Nichols - Jesse Siglow (Episode: \"Family Limitation (2010)\")\r\n                </td>\r\n            </tr>\r\n            <tr>\r\n                <td>\r\n                    <b>2011 Nominee HPA Award</b>\r\n                    <br />\r\n                    Outstanding Compositing - Television\r\n                    <br />\r\n                    J. John Corbett - Jun Zhang - Matthew Conner (Episode: \"Boardwalk Empire (2010)\")\r\n                </td>\r\n            </tr>\r\n        </tbody>\r\n    </table>\r\n    <h3>NAMIC Vision Awards</h3>\r\n    <table>\r\n        <tbody>\r\n            <tr>\r\n                <td>\r\n                    <b>2015 Winner Vision Award</b>\r\n                    <br />\r\n                    Best Performance - Drama\r\n                    <br />\r\n                    Michael Kenneth Williams\r\n                </td>\r\n            </tr>\r\n            <tr>\r\n                <td>\r\n                    <b>2015 Nominee Vision Award</b>\r\n                    <br />\r\n                    Best Performance - Drama\r\n                    <br />\r\n                    Jeffrey Wright\r\n                </td>\r\n            </tr>\r\n            <tr>\r\n                <td>\r\n                    <b>2015 Nominee Vision Award</b>\r\n                    <br />\r\n                    Best Performance - Drama\r\n                    <br />\r\n                    Margot Bingham\r\n                </td>\r\n            </tr>\r\n            <tr>\r\n                <td>\r\n                    <b>2014 Nominee Vision Award</b>\r\n                    <br />\r\n                    Best Performance - Drama\r\n                    <br />\r\n                    Michael Kenneth Williams\r\n                </td>\r\n            </tr>\r\n            <tr>\r\n                <td>\r\n                    <b>2014 Winner Vision Award</b>\r\n                    <br />\r\n                    Best Performance - Drama\r\n                    <br />\r\n                    Jeffrey Wright\r\n                </td>\r\n            </tr>\r\n        </tbody>\r\n    </table>\r\n    <h3>Location Managers Guild International Awards (LMGI)</h3>\r\n    <table>\r\n        <tbody>\r\n            <tr>\r\n                <td>\r\n                    <b>2015 Winner LMGI Award</b>\r\n                    <br />\r\n                    Outstanding Locations in a Period Television Series\r\n                    <br />\r\n                    Amanda Foley - Audra Gorman\r\n                </td>\r\n            </tr>\r\n        </tbody>\r\n    </table>\r\n    <h3>Motion Picture Sound Editors, USA</h3>\r\n    <table>\r\n        <tbody>\r\n            <tr>\r\n                <td>\r\n                    <b>2014 Nominee Golden Reel Award</b>\r\n                    <br />\r\n                    Best Sound Editing - Short Form Dialogue and ADR in Television\r\n                    <br />\r\n                    Fred Rosenberg (supervising sound editor, supervising adr editor, adr editor) - Jeffrey Stern (supervising dialogue editor, dialogue editor) - Bill Orrico (dialogue editor) - Roland Vajs (dialogue editor) (Episode: \"Havre de Grace\")\r\n                </td>\r\n            </tr>\r\n            <tr>\r\n                <td>\r\n                    <b>2014 Nominee Golden Reel Award</b>\r\n                    <br />\r\n                    Best Sound Editing - Short Form Sound Effects and Foley in Television\r\n                    <br />\r\n                    Fred Rosenberg (supervising sound editor) - Ruy García (sound designer) - Steven Visscher (supervising foley editor) - Marko A. Costanzo (foley artist) - Bill Orrico (foley editor) - Roland Vajs (effects editor) (Episode: \"White Horse Pike\")\r\n                </td>\r\n            </tr>\r\n            <tr>\r\n                <td>\r\n                    <b>2011 Winner Golden Reel Award</b>\r\n                    <br />\r\n                    Best Sound Editing - Short Form Music in Television\r\n                    <br />\r\n                    Annette Kudrak (music editor) (Episode: \"Anastasia\")\r\n                </td>\r\n            </tr>\r\n        </tbody>\r\n    </table>\r\n    <h3>Critics Choice Television Awards</h3>\r\n    <table>\r\n        <tbody>\r\n            <tr>\r\n                <td>\r\n                    <b>2014 Nominee Critics' Choice TV Award</b>\r\n                    <br />\r\n                    Best Supporting Actor in a Drama Series\r\n                    <br />\r\n                    Jeffrey Wright\r\n                </td>\r\n            </tr>\r\n            <tr>\r\n                <td>\r\n                    <b>2012 Nominee Critics' Choice TV Award</b>\r\n                    <br />\r\n                    Best Supporting Actress in a Drama Series\r\n                    <br />\r\n                    Kelly Macdonald\r\n                </td>\r\n            </tr>\r\n            <tr>\r\n                <td>\r\n                    <b>2011 Nominee Critics' Choice TV Award</b>\r\n                    <br />\r\n                    Best Drama Series\r\n                </td>\r\n            </tr>\r\n            <tr>\r\n                <td>\r\n                    <b>2011 Nominee Critics' Choice TV Award</b>\r\n                    <br />\r\n                    Best Actor in a Drama Series\r\n                    <br />\r\n                    Steve Buscemi\r\n                </td>\r\n            </tr>\r\n            <tr>\r\n                <td>\r\n                    <b>2011 Nominee Critics' Choice TV Award</b>\r\n                    <br />\r\n                    Best Supporting Actor in a Drama Series\r\n                    <br />\r\n                    Michael Pitt\r\n                </td>\r\n            </tr>\r\n        </tbody>\r\n    </table>\r\n    <h3>Guild of Music Supervisors Awards</h3>\r\n    <table>\r\n        <tbody>\r\n            <tr>\r\n                <td>\r\n                    <b>2014 Nominee GMS Award</b>\r\n                    <br />\r\n                    Best Music Supervision for Television Drama\r\n                    <br />\r\n                    Randall Poster\r\n                </td>\r\n            </tr>\r\n            <tr>\r\n                <td>\r\n                    <b>2013 Nominee GMS Award</b>\r\n                    <br />\r\n                    Best Music Supervision for Television Drama\r\n                    <br />\r\n                    Randall Poster\r\n                </td>\r\n            </tr>\r\n            <tr>\r\n                <td>\r\n                    <b>2011 Nominee GMS Award</b>\r\n                    <br />\r\n                    Best Music Supervision for Television\r\n                    <br />\r\n                    Jim Dunbar - Randall Poster\r\n                </td>\r\n            </tr>\r\n        </tbody>\r\n    </table>\r\n    <h3>Golden Globes, USA</h3>\r\n    <table>\r\n        <tbody>\r\n            <tr>\r\n                <td>\r\n                    <b>2013 Nominee Golden Globe</b>\r\n                    <br />\r\n                    Best Television Series - Drama\r\n                </td>\r\n            </tr>\r\n            <tr>\r\n                <td>\r\n                    <b>2013 Nominee Golden Globe</b>\r\n                    <br />\r\n                    Best Performance by an Actor in a Television Series - Drama\r\n                    <br />\r\n                    Steve Buscemi\r\n                </td>\r\n            </tr>\r\n            <tr>\r\n                <td>\r\n                    <b>2012 Nominee Golden Globe</b>\r\n                    <br />\r\n                    Best Television Series - Drama\r\n                </td>\r\n            </tr>\r\n            <tr>\r\n                <td>\r\n                    <b>2012 Nominee Golden Globe</b>\r\n                    <br />\r\n                    Best Performance by an Actor in a Television Series - Drama\r\n                    <br />\r\n                    Steve Buscemi\r\n                </td>\r\n            </tr>\r\n            <tr>\r\n                <td>\r\n                    <b>2012 Nominee Golden Globe</b>\r\n                    <br />\r\n                    Best Performance by an Actress in a Supporting Role in a Series, Miniseries or Motion Picture Made for Television\r\n                    <br />\r\n                    Kelly Macdonald\r\n                </td>\r\n            </tr>\r\n        </tbody>\r\n    </table>\r\n    <h3>Key Art Awards</h3>\r\n    <table>\r\n        <tbody>\r\n            <tr>\r\n                <td>\r\n                    <b>2013 Nominee Key Art Award</b>\r\n                    <br />\r\n                    Best Engagement\r\n                    <br />\r\n                     (For the TV spot, \"Boardwalk Empire/Uber Promotional Stunt\".)\r\n                </td>\r\n            </tr>\r\n        </tbody>\r\n    </table>\r\n    <h3>Crime Thriller Awards, UK</h3>\r\n    <table>\r\n        <tbody>\r\n            <tr>\r\n                <td>\r\n                    <b>2013 Nominee Dagger</b>\r\n                    <br />\r\n                    Best International TV Drama\r\n                    <br />\r\n                     (\"Season 3\")\r\n                </td>\r\n            </tr>\r\n            <tr>\r\n                <td>\r\n                    <b>2012 Winner Dagger</b>\r\n                    <br />\r\n                    Best Supporting Actress\r\n                    <br />\r\n                    Kelly Macdonald\r\n                </td>\r\n            </tr>\r\n            <tr>\r\n                <td>\r\n                    <b>2012 Nominee Dagger</b>\r\n                    <br />\r\n                    Best Leading Actor\r\n                    <br />\r\n                    Steve Buscemi\r\n                </td>\r\n            </tr>\r\n            <tr>\r\n                <td>\r\n                    <b>2012 Nominee Dagger</b>\r\n                    <br />\r\n                    Best International TV Drama\r\n                    <br />\r\n                     (\"Season 2\")\r\n                </td>\r\n            </tr>\r\n            <tr>\r\n                <td>\r\n                    <b>2011 Nominee Dagger</b>\r\n                    <br />\r\n                    Best Leading Actor\r\n                    <br />\r\n                    Steve Buscemi\r\n                </td>\r\n            </tr>\r\n        </tbody>\r\n    </table>\r\n    <h3>IGN Summer Movie Awards</h3>\r\n    <table>\r\n        <tbody>\r\n            <tr>\r\n                <td>\r\n                    <b>2013 Nominee IGN Award</b>\r\n                    <br />\r\n                    Best TV Villain\r\n                    <br />\r\n                    Jeffrey Wright (For playing \"Dr. Valentin Narcisse\".)\r\n                </td>\r\n            </tr>\r\n            <tr>\r\n                <td>\r\n                    <b>2012 Winner IGN Award</b>\r\n                    <br />\r\n                    Best TV Villain\r\n                    <br />\r\n                    Bobby Cannavale (For playing \"Gyp Rosetti\".)\r\n                </td>\r\n            </tr>\r\n            <tr>\r\n                <td>\r\n                    <b>2011 Nominee IGN Award</b>\r\n                    <br />\r\n                    Best TV Episode\r\n                    <br />\r\n                     (For the episode \"Under God's Power She Flourishes\".)\r\n                </td>\r\n            </tr>\r\n            <tr>\r\n                <td>\r\n                    <b>2010 Nominee IGN Award</b>\r\n                    <br />\r\n                    Best New TV Series\r\n                </td>\r\n            </tr>\r\n        </tbody>\r\n    </table>\r\n    <h3>Visual Effects Society Awards</h3>\r\n    <table>\r\n        <tbody>\r\n            <tr>\r\n                <td>\r\n                    <b>2013 Winner VES Award</b>\r\n                    <br />\r\n                    Outstanding Supporting Visual Effects in a Broadcast Program\r\n                    <br />\r\n                    John Bair - Parker Chehak - Paul Graff - Lesley Robson-Foster (Episode: \"The Pony (2012)\")\r\n                </td>\r\n            </tr>\r\n            <tr>\r\n                <td>\r\n                    <b>2012 Winner VES Award</b>\r\n                    <br />\r\n                    Outstanding Models in a Broadcast Program or Commercial\r\n                    <br />\r\n                    Matthew Conner - Eran Dinur - David W. Reynolds - Szymon Weglarski (Georgia Peaches)\r\n                </td>\r\n            </tr>\r\n            <tr>\r\n                <td>\r\n                    <b>2012 Nominee VES Award</b>\r\n                    <br />\r\n                    Outstanding Created Environment in a Broadcast Program or Commercial\r\n                    <br />\r\n                    Matthew Conner - Robert Stromberg (\"Two Boats and a Lifeguard\")\r\n                </td>\r\n            </tr>\r\n            <tr>\r\n                <td>\r\n                    <b>2012 Nominee VES Award</b>\r\n                    <br />\r\n                    Outstanding Supporting Visual Effects in a Broadcast Program\r\n                    <br />\r\n                    Richard Friedlander - Robert Stromberg - David Taritero (Episode: \"Georgia Peaches (2011)\")\r\n                </td>\r\n            </tr>\r\n            <tr>\r\n                <td>\r\n                    <b>2012 Winner VES Award</b>\r\n                    <br />\r\n                    Outstanding Compositing in a Broadcast Program or Commercial\r\n                    <br />\r\n                    Anton Dawson - Eran Dinur - Austin Meyers - David W. Reynolds (Episode: \"Gimcrack and Bunkum (2011)\")\r\n                </td>\r\n            </tr>\r\n        </tbody>\r\n    </table>\r\n    <h3>Young Artist Awards</h3>\r\n    <table>\r\n        <tbody>\r\n            <tr>\r\n                <td>\r\n                    <b>2013 Winner Young Artist Award</b>\r\n                    <br />\r\n                    Best Performance in a TV Series - Recurring Young Actor Ten and Under\r\n                    <br />\r\n                    Rory McTigue - Declan McTigue\r\n                </td>\r\n            </tr>\r\n            <tr>\r\n                <td>\r\n                    <b>2013 Nominee Young Artist Award</b>\r\n                    <br />\r\n                    Best Performance in a TV Series - Recurring Young Actress\r\n                    <br />\r\n                    Lucy Gallina - Josie Gallina\r\n                </td>\r\n            </tr>\r\n            <tr>\r\n                <td>\r\n                    <b>2012 Nominee Young Artist Award</b>\r\n                    <br />\r\n                    Best Performance in a TV Series - Recurring Young Actor\r\n                    <br />\r\n                    Brady Noon (as Brady & Connor Noon) - Connor Noon (as Brady & Connor Noon)\r\n                </td>\r\n            </tr>\r\n            <tr>\r\n                <td>\r\n                    <b>2012 Nominee Young Artist Award</b>\r\n                    <br />\r\n                    Best Performance in a TV Series - Recurring Young Actress Ten and Under\r\n                    <br />\r\n                    Lucy Gallina (as Lucy and Josie Gallina) - Josie Gallina (as Lucy and Josie Gallina)\r\n                </td>\r\n            </tr>\r\n        </tbody>\r\n    </table>\r\n    <h3>Grammy Awards</h3>\r\n    <table>\r\n        <tbody>\r\n            <tr>\r\n                <td>\r\n                    <b>2012 Winner Grammy</b>\r\n                    <br />\r\n                    Best Compilation Soundtrack Album for Motion Picture, Television or Other Visual Media\r\n                    <br />\r\n                    Stewart Lerman (Producer) - Randall Poster (Producer) - Kevin Weaver (Producer)\r\n                </td>\r\n            </tr>\r\n        </tbody>\r\n    </table>\r\n    <h3>AFI Awards, USA</h3>\r\n    <table>\r\n        <tbody>\r\n            <tr>\r\n                <td>\r\n                    <b>2012 Winner AFI Award</b>\r\n                    <br />\r\n                    TV Program of the Year\r\n                    <br />\r\n                     (BOARDWALK EMPIRE struts into its second year with an intoxicating air, adding new layers of complexity to this sumptuous, sprawling saga of Atlantic City during Prohibition. Martin Scorsese and Terence Winter command a talented ensemble that tells a tale of America, this year uncorking the emotional inner life of Steve Buscemi's \"Nucky Thompson\" and the world he rules with an iron fist.)\r\n                </td>\r\n            </tr>\r\n            <tr>\r\n                <td>\r\n                    <b>2011 Winner AFI Award</b>\r\n                    <br />\r\n                    TV Program of the Year\r\n                    <br />\r\n                     (BOARDWALK EMPIRE struts into its second year with an intoxicating air, adding new layers of complexity to this sumptuous, sprawling saga of Atlantic City during Prohibition. Martin Scorsese and Terence Winter command a talented ensemble that tells a tale of America, this year uncorking the emotional inner life of Steve Buscemi's \"Nucky Thompson\" and the world he rules with an iron fist.)\r\n                </td>\r\n            </tr>\r\n        </tbody>\r\n    </table>\r\n    <h3>American Cinema Editors, USA</h3>\r\n    <table>\r\n        <tbody>\r\n            <tr>\r\n                <td>\r\n                    <b>2012 Nominee Eddie</b>\r\n                    <br />\r\n                    Best Edited One-Hour Series for Non-Commercial Television\r\n                    <br />\r\n                    Tim Streeto (Episode: \"To the Lost (2011)\")\r\n                </td>\r\n            </tr>\r\n            <tr>\r\n                <td>\r\n                    <b>2011 Nominee Eddie</b>\r\n                    <br />\r\n                    Best Edited One-Hour Series for Non-Commercial Television\r\n                    <br />\r\n                    Sidney Wolinsky (Episode: \"Boardwalk Empire (2010)\")\r\n                </td>\r\n            </tr>\r\n        </tbody>\r\n    </table>\r\n    <h3>Monte-Carlo TV Festival</h3>\r\n    <table>\r\n        <tbody>\r\n            <tr>\r\n                <td>\r\n                    <b>2012 Nominee Golden Nymph</b>\r\n                    <br />\r\n                    Outstanding Actor in a Drama Series\r\n                    <br />\r\n                    Steve Buscemi\r\n                </td>\r\n            </tr>\r\n            <tr>\r\n                <td>\r\n                    <b>2012 Nominee Golden Nymph</b>\r\n                    <br />\r\n                    Outstanding Actor in a Drama Series\r\n                    <br />\r\n                    Michael Pitt\r\n                </td>\r\n            </tr>\r\n            <tr>\r\n                <td>\r\n                    <b>2012 Nominee Golden Nymph</b>\r\n                    <br />\r\n                    Outstanding Actress in a Drama Series\r\n                    <br />\r\n                    Kelly Macdonald\r\n                </td>\r\n            </tr>\r\n            <tr>\r\n                <td>\r\n                    <b>2012 Nominee Golden Nymph</b>\r\n                    <br />\r\n                    Outstanding Actress in a Drama Series\r\n                    <br />\r\n                    Gretchen Mol\r\n                </td>\r\n            </tr>\r\n            <tr>\r\n                <td>\r\n                    <b>2012 Nominee Golden Nymph</b>\r\n                    <br />\r\n                    Outstanding International Producer (Drama Series)\r\n                    <br />\r\n                    Martin Scorsese - Mark Wahlberg - Terence Winter - Timothy Van Patten - Stephen Levinson\r\n                </td>\r\n            </tr>\r\n        </tbody>\r\n    </table>\r\n    <h3>Banff Television Festival</h3>\r\n    <table>\r\n        <tbody>\r\n            <tr>\r\n                <td>\r\n                    <b>2012 Winner Banff Rockie Award</b>\r\n                    <br />\r\n                    Best Continuing Series\r\n                    <br />\r\n                    Terence Winter (writer) - Timothy Van Patten (director) (For episode '21' (USA))\r\n                </td>\r\n            </tr>\r\n            <tr>\r\n                <td>\r\n                    <b>2011 Nominee Banff Rockie Award</b>\r\n                    <br />\r\n                    Best Continuing Series\r\n                    <br />\r\n                    Timothy Van Patten - Martin Scorsese - Terence Winter - Howard Korder (For episode 'Boardwalk Empire' (USA))\r\n                </td>\r\n            </tr>\r\n        </tbody>\r\n    </table>\r\n    <h3>PGA Awards</h3>\r\n    <table>\r\n        <tbody>\r\n            <tr>\r\n                <td>\r\n                    <b>2012 Winner PGA Award</b>\r\n                    <br />\r\n                    Outstanding Producer of Episodic Television, Drama\r\n                    <br />\r\n                    Eugene Kelly - Howard Korder - Stephen Levinson - Martin Scorsese - Rudd Simmons - Timothy Van Patten - Terence Winter\r\n                </td>\r\n            </tr>\r\n        </tbody>\r\n    </table>\r\n    <h3>Women's Image Network Awards</h3>\r\n    <table>\r\n        <tbody>\r\n            <tr>\r\n                <td>\r\n                    <b>2012 Nominee WIN Award</b>\r\n                    <br />\r\n                    Actress Drama Series\r\n                    <br />\r\n                    Kelly Macdonald\r\n                </td>\r\n            </tr>\r\n        </tbody>\r\n    </table>\r\n    <h3>Directors Guild of America, USA</h3>\r\n    <table>\r\n        <tbody>\r\n            <tr>\r\n                <td>\r\n                    <b>2011 Nominee DGA Award</b>\r\n                    <br />\r\n                    Outstanding Directorial Achievement in Dramatic Series\r\n                    <br />\r\n                    Allen Coulter (For episode \"Paris Green\")\r\n                </td>\r\n            </tr>\r\n            <tr>\r\n                <td>\r\n                    <b>2011 Winner DGA Award</b>\r\n                    <br />\r\n                    Outstanding Directorial Achievement in Dramatic Series\r\n                    <br />\r\n                    Martin Scorsese - Harvey Waldman (unit production manager) (plaque) - Christopher Surgent (first assistant director) (plaque) - Takahide Kawakami (second assistant director) (plaque) - April Taylor (second assistant director/location manager) (plaque) - Regina Heyman (second assistant director/location manager) (plaque) - Patrick McDonald (second second assistant director) (plaque) - Salvatore E. Sutera (additional second assistant director) (plaque) (For episode \"Boardwalk Empire\")\r\n                </td>\r\n            </tr>\r\n        </tbody>\r\n    </table>\r\n    <h3>Television Critics Association Awards</h3>\r\n    <table>\r\n        <tbody>\r\n            <tr>\r\n                <td>\r\n                    <b>2011 Nominee TCA Award</b>\r\n                    <br />\r\n                    Program of the Year\r\n                </td>\r\n            </tr>\r\n            <tr>\r\n                <td>\r\n                    <b>2011 Nominee TCA Award</b>\r\n                    <br />\r\n                    Outstanding New Program\r\n                </td>\r\n            </tr>\r\n            <tr>\r\n                <td>\r\n                    <b>2011 Nominee TCA Award</b>\r\n                    <br />\r\n                    Individual Achievement in Drama\r\n                    <br />\r\n                    Steve Buscemi\r\n                </td>\r\n            </tr>\r\n        </tbody>\r\n    </table>\r\n    <h3>Casting Society of America, USA</h3>\r\n    <table>\r\n        <tbody>\r\n            <tr>\r\n                <td>\r\n                    <b>2011 Winner Artios Award</b>\r\n                    <br />\r\n                    Outstanding Achievement in Casting - Television Pilot - Drama\r\n                    <br />\r\n                    Ellen Lewis (Casting Director)\r\n                </td>\r\n            </tr>\r\n        </tbody>\r\n    </table>\r\n    <h3>Satellite Awards</h3>\r\n    <table>\r\n        <tbody>\r\n            <tr>\r\n                <td>\r\n                    <b>2011 Nominee Satellite Award</b>\r\n                    <br />\r\n                    Best Actress in a Supporting Role in a Series, Mini-Series or Motion Picture Made for Television\r\n                    <br />\r\n                    Kelly Macdonald\r\n                </td>\r\n            </tr>\r\n            <tr>\r\n                <td>\r\n                    <b>2011 Nominee Satellite Award</b>\r\n                    <br />\r\n                    Best Television Series, Drama\r\n                </td>\r\n            </tr>\r\n            <tr>\r\n                <td>\r\n                    <b>2011 Nominee Satellite Award</b>\r\n                    <br />\r\n                    Best Actor in a Series, Drama\r\n                    <br />\r\n                    Steve Buscemi\r\n                </td>\r\n            </tr>\r\n            <tr>\r\n                <td>\r\n                    <b>2010 Nominee Satellite Award</b>\r\n                    <br />\r\n                    Best Television Series, Drama\r\n                </td>\r\n            </tr>\r\n        </tbody>\r\n    </table>\r\n    <h3>GALECA: The Society of LGBTQ Entertainment Critics</h3>\r\n    <table>\r\n        <tbody>\r\n            <tr>\r\n                <td>\r\n                    <b>2011 Nominee Dorian Award</b>\r\n                    <br />\r\n                    TV Drama of the Year\r\n                </td>\r\n            </tr>\r\n        </tbody>\r\n    </table>\r\n    <h3>Gold Derby Awards</h3>\r\n    <table>\r\n        <tbody>\r\n            <tr>\r\n                <td>\r\n                    <b>2011 Nominee Gold Derby TV Award</b>\r\n                    <br />\r\n                    Drama Series\r\n                </td>\r\n            </tr>\r\n            <tr>\r\n                <td>\r\n                    <b>2011 Nominee Gold Derby TV Award</b>\r\n                    <br />\r\n                    Drama Lead Actor\r\n                    <br />\r\n                    Steve Buscemi\r\n                </td>\r\n            </tr>\r\n            <tr>\r\n                <td>\r\n                    <b>2011 Nominee Gold Derby TV Award</b>\r\n                    <br />\r\n                    Drama Supporting Actress\r\n                    <br />\r\n                    Kelly Macdonald\r\n                </td>\r\n            </tr>\r\n        </tbody>\r\n    </table>\r\n    <h3>Il Festival Nazionale del Doppiaggio Voci nell'Ombra</h3>\r\n    <table>\r\n        <tbody>\r\n            <tr>\r\n                <td>\r\n                    <b>2011 Nominee TV Award</b>\r\n                    <br />\r\n                    Best Dubbing Direction\r\n                    <br />\r\n                    Sonia Scotti\r\n                </td>\r\n            </tr>\r\n        </tbody>\r\n    </table>\r\n</div>\r\n",
  "errorMessage": ""
}